[{"id": "tq3fzHSEbvI", "title": "12 Juli 2026", "channel": "F1rz.a", "channel_id": "UCLAal2514ZVEuf2yZkJVgbw", "thumbnail": "https://i.ytimg.com/vi/tq3fzHSEbvI/hqdefault.jpg", "duration_s": 40, "is_vertical": false, "views": 211}, {"id": "qKGsPCnda0k", "title": "12 Juli 2026", "channel": "Daffa Mandala", "channel_id": "UC1q0t5o3caL3SAWWtEuwRNA", "thumbnail": "https://i.ytimg.com/vi/qKGsPCnda0k/hqdefault.jpg", "duration_s": 50, "is_vertical": false, "views": 203}, {"id": "W6KXG3DC1IU", "title": "12 Juli 2026", "channel": "Nadira Hadid", "channel_id": "UCvVN4dEySjD9tTwJEzpxAFA", "thumbnail": "https://i.ytimg.com/vi/W6KXG3DC1IU/hqdefault.jpg", "duration_s": 61, "is_vertical": false, "views": 200}, {"id": "3bw0Sphq6O0", "title": "12 Juli 2026", "channel": "Adnan ", "channel_id": "UCCh9YhzfaKaD_G0l_3LiMBA", "thumbnail": "https://i.ytimg.com/vi/3bw0Sphq6O0/hqdefault.jpg", "duration_s": 31, "is_vertical": false, "views": 288}, {"id": "AXSZyc3jdTQ", "title": "12. Juli 2026", "channel": "OstRingen TV", "channel_id": "UCQK0NklL9RscuQRnCU3SJtw", "thumbnail": "https://i.ytimg.com/vi/AXSZyc3jdTQ/hqdefault.jpg", "duration_s": 29, "is_vertical": false, "views": 284}, {"id": "kZVrlDeO7Ck", "title": "12 Juli 2026", "channel": "محمد يزيد البناني", "channel_id": "UCR72SdQaxdY5sk5AiNFzutw", "thumbnail": "https://i.ytimg.com/vi/kZVrlDeO7Ck/hqdefault.jpg", "duration_s": 162, "is_vertical": false, "views": 84}, {"id": "oXAHWL5fO-M", "title": "12. Juli 2026", "channel": "Germanblox", "channel_id": "UCaQIVSV6bBtwaEjCZnH6mLg", "thumbnail": "https://i.ytimg.com/vi/oXAHWL5fO-M/hqdefault.jpg", "duration_s": 37, "is_vertical": false, "views": 327}, {"id": "OVHmes-ZYJE", "title": "July 12, 2026", "channel": "Sonique Saturday", "channel_id": "UCQw6FibxVBaWoXX9i2dZk3w", "thumbnail": "https://i.ytimg.com/vi/OVHmes-ZYJE/hqdefault.jpg", "duration_s": 25, "is_vertical": false, "views": 363}, {"id": "jbuiEOckjzM", "title": "12. Juli 2026", "channel": "Mittelstand bewegt", "channel_id": "UCYNxE7GcVQafsfTVDDk_lzA", "thumbnail": "https://i.ytimg.com/vi/jbuiEOckjzM/hqdefault.jpg", "duration_s": 34, "is_vertical": false, "views": 446}, {"id": "oBhjhzrLYlQ", "title": "12 Juli 2026", "channel": "Fata Illahi", "channel_id": "UCcsvUZr0ziP4nJWxxqvRq7A", "thumbnail": "https://i.ytimg.com/vi/oBhjhzrLYlQ/hqdefault.jpg", "duration_s": 20, "is_vertical": false, "views": 564}, {"id": "tkqal88hv4Q", "title": "12 Juli 2026", "channel": "Korvax", "channel_id": "UCMGVzbAqnli32_VCyFN7C9g", "thumbnail": "https://i.ytimg.com/vi/tkqal88hv4Q/hqdefault.jpg", "duration_s": 85, "is_vertical": false, "views": 863}, {"id": "DNy8n7zEwXs", "title": "July 12, 2026", "channel": "Sonique Saturday", "channel_id": "UCQw6FibxVBaWoXX9i2dZk3w", "thumbnail": "https://i.ytimg.com/vi/DNy8n7zEwXs/hqdefault.jpg", "duration_s": 56, "is_vertical": false, "views": 250}, {"id": "4sX6IqMfLvU", "title": "12 Juli 2026", "channel": "RUANG ILMU CHANNEL", "channel_id": "UCAirNyTy5wJEPzBbAyGib8w", "thumbnail": "https://i.ytimg.com/vi/4sX6IqMfLvU/hqdefault.jpg", "duration_s": 142, "is_vertical": false, "views": 429}, {"id": "kccufT7wzW4", "title": "12 Juli 2026", "channel": "UD CLO", "channel_id": "UCbWQDFOZL22f-2cO_Od-ezA", "thumbnail": "https://i.ytimg.com/vi/kccufT7wzW4/hqdefault.jpg", "duration_s": 28, "is_vertical": false, "views": 421}, {"id": "DYehJhKcCeE", "title": "12 Juli 2026", "channel": "Ghufran Ramadhan ", "channel_id": "UC9jmQ38gLdiYY5Q2nl-MXgA", "thumbnail": "https://i.ytimg.com/vi/DYehJhKcCeE/hqdefault.jpg", "duration_s": 18, "is_vertical": false, "views": 821}, {"id": "aCFsECH5U7g", "title": "12. Juli 2026", "channel": "Jamal Hakimi", "channel_id": "UCav8BA4L4565cjD8w090Bsg", "thumbnail": "https://i.ytimg.com/vi/aCFsECH5U7g/hqdefault.jpg", "duration_s": 50, "is_vertical": false, "views": 464}, {"id": "x7Nx2RNHW4o", "title": "2026年7月12日", "channel": "SuperSofa", "channel_id": "UC6POjXxNgZY0qTRLqQpZPNg", "thumbnail": "https://i.ytimg.com/vi/x7Nx2RNHW4o/hqdefault.jpg", "duration_s": 17, "is_vertical": false, "views": 531}, {"id": "l-6r9VIb0eQ", "title": "12 juli 2026", "channel": "Aya Alhaj اية الحج", "channel_id": "UC4laRxm5vTjayCGe1fpsZtg", "thumbnail": "https://i.ytimg.com/vi/l-6r9VIb0eQ/hqdefault.jpg", "duration_s": 68, "is_vertical": false, "views": 66387}, {"id": "GaPp1d95Fuc", "title": "12 Juli 2026", "channel": "Bopal", "channel_id": "UCXJZ6mfcNdeJGM1XT2Q7IEQ", "thumbnail": "https://i.ytimg.com/vi/GaPp1d95Fuc/hqdefault.jpg", "duration_s": 46, "is_vertical": false, "views": 498}, {"id": "Hqv8ojpxk9s", "title": "12 Juli 2026", "channel": "Ita Reziana", "channel_id": "UCITmyE7B4nOEYgBlNUiv3Hg", "thumbnail": "https://i.ytimg.com/vi/Hqv8ojpxk9s/hqdefault.jpg", "duration_s": 26, "is_vertical": false, "views": 748}, {"id": "SocYxd0L-n8", "title": "12. Juli 2026", "channel": "Niklas Behnke", "channel_id": "UC8Bh1BT4Tw7LypQkK0L4GOA", "thumbnail": "https://i.ytimg.com/vi/SocYxd0L-n8/hqdefault.jpg", "duration_s": 27, "is_vertical": false, "views": 630}, {"id": "bmGE1YpMfWo", "title": "12 Juli 2026", "channel": "TENZO X7", "channel_id": "UCq6okWsBakjVCrR9nr4mZSw", "thumbnail": "https://i.ytimg.com/vi/bmGE1YpMfWo/hqdefault.jpg", "duration_s": 23, "is_vertical": false, "views": 475}, {"id": "BTMyn_HKTEg", "title": "12 Juli 2026", "channel": " ★FF_Gaming_PRO★", "channel_id": "UCAQ8j_e6-n5fkfSccANbaIw", "thumbnail": "https://i.ytimg.com/vi/BTMyn_HKTEg/hqdefault.jpg", "duration_s": 24, "is_vertical": false, "views": 882}, {"id": "c77xbHsESbk", "title": "12. Juli 2026", "channel": "Minasschoki", "channel_id": "UCzee8jDsqyscbmFQJsSjfXw", "thumbnail": "https://i.ytimg.com/vi/c77xbHsESbk/hqdefault.jpg", "duration_s": 27, "is_vertical": false, "views": 650}, {"id": "1pLWFkLIDpQ", "title": "12 Juli 2026", "channel": "ap king v4 edisi bagus bajing", "channel_id": "UC1hZkoOEMqwtMZdYIwnmGfg", "thumbnail": "https://i.ytimg.com/vi/1pLWFkLIDpQ/hqdefault.jpg", "duration_s": 21, "is_vertical": false, "views": 756}, {"id": "sFOu6eFWxcE", "title": "Tv9 Marathi News Top Headline Today | 12 July 2026 | 4 Minute 24 Headline Maharashtra", "channel": "TV9 Marathi", "channel_id": "UCdOSeEq9Cs2Pco7OCn2_i5w", "thumbnail": "https://i.ytimg.com/vi/sFOu6eFWxcE/hqdefault.jpg", "duration_s": 79, "is_vertical": false, "views": 15881}, {"id": "FRFR2yn-R9Q", "title": "12 Juli 2026", "channel": "AlFio custom", "channel_id": "UCCwamKdk9M-dt8vJXc4S-lg", "thumbnail": "https://i.ytimg.com/vi/FRFR2yn-R9Q/hqdefault.jpg", "duration_s": 20, "is_vertical": false, "views": 906}, {"id": "-sD-tDj-1rc", "title": "July 12, 2026", "channel": "Thor Deep", "channel_id": "UCixCwFDLg6ZGCtGv2aFn10A", "thumbnail": "https://i.ytimg.com/vi/-sD-tDj-1rc/hqdefault.jpg", "duration_s": 25, "is_vertical": false, "views": 554}, {"id": "YtoinV1QkM4", "title": "12 Juli 2026", "channel": "Yasi Kem", "channel_id": "UCezC-ucdoiEKd_hpmvEoq5g", "thumbnail": "https://i.ytimg.com/vi/YtoinV1QkM4/hqdefault.jpg", "duration_s": 59, "is_vertical": false, "views": 677}, {"id": "KwmX2KcW5FI", "title": "12 Juli 2026", "channel": "Paman Jalan Jalan", "channel_id": "UCsCP_aifc5dFIC51La4mPQA", "thumbnail": "https://i.ytimg.com/vi/KwmX2KcW5FI/hqdefault.jpg", "duration_s": 39, "is_vertical": false, "views": 736}, {"id": "q_TnVkXa6Ls", "title": "12. Juli 2026", "channel": "Kochfreaks", "channel_id": "UCsmgfggPiugjtvGegpHb6Ew", "thumbnail": "https://i.ytimg.com/vi/q_TnVkXa6Ls/hqdefault.jpg", "duration_s": 94, "is_vertical": false, "views": 683}, {"id": "KLLVUuOSD2A", "title": "July 12, 2026", "channel": "Dare to Ask", "channel_id": "UCI1rtpK1Vvk9dr7DKMT28RA", "thumbnail": "https://i.ytimg.com/vi/KLLVUuOSD2A/hqdefault.jpg", "duration_s": 26, "is_vertical": false, "views": 969}, {"id": "O0n5zomAOwE", "title": "12 Juli 2026", "channel": "lisya?!", "channel_id": "UCecFNOViWCv-LGykfz3FMNw", "thumbnail": "https://i.ytimg.com/vi/O0n5zomAOwE/hqdefault.jpg", "duration_s": 23, "is_vertical": false, "views": 716}, {"id": "gbgmthRaDWo", "title": "12 Juli 2026", "channel": "ZAHRA COMEL", "channel_id": "UCUpRJV6O4p-k0PMsQf7V0EA", "thumbnail": "https://i.ytimg.com/vi/gbgmthRaDWo/hqdefault.jpg", "duration_s": 43, "is_vertical": false, "views": 907}, {"id": "-Uuieal7wQY", "title": "July 12, 2026", "channel": "NguyenLonzuy", "channel_id": "UCVO7PuAlKfpygSsralpwsFg", "thumbnail": "https://i.ytimg.com/vi/-Uuieal7wQY/hqdefault.jpg", "duration_s": 61, "is_vertical": false, "views": 529}, {"id": "hpY6zS-vNww", "title": "12 Juli 2026", "channel": "Mareti Nursyalena", "channel_id": "UC1_Bk14GJD96VbjJ20GZwwg", "thumbnail": "https://i.ytimg.com/vi/hpY6zS-vNww/hqdefault.jpg", "duration_s": 94, "is_vertical": false, "views": 449}, {"id": "coFPuXMc4NI", "title": "12 Juli 2026", "channel": "intan putri", "channel_id": "UCEF4wNlF8GT1mu0iKYPRvcw", "thumbnail": "https://i.ytimg.com/vi/coFPuXMc4NI/hqdefault.jpg", "duration_s": 35, "is_vertical": false, "views": 325}, {"id": "b39S68o2f_Y", "title": "12. Juli 2026", "channel": "Liah süs ", "channel_id": "UCZW8NFecAWrljnXMDXMJSEQ", "thumbnail": "https://i.ytimg.com/vi/b39S68o2f_Y/hqdefault.jpg", "duration_s": 58, "is_vertical": false, "views": 907}, {"id": "gdj07IhbuFQ", "title": "12 Juli 2026", "channel": "Vawas Roy", "channel_id": "UC65v39uTRCUNCGCFZHYz-ow", "thumbnail": "https://i.ytimg.com/vi/gdj07IhbuFQ/hqdefault.jpg", "duration_s": 46, "is_vertical": false, "views": 568}, {"id": "3f9ul7RGXzE", "title": "12 Juli 2026", "channel": "@andrast", "channel_id": "UCSb7CUfLfR8HWTQ8GPBz7DQ", "thumbnail": "https://i.ytimg.com/vi/3f9ul7RGXzE/hqdefault.jpg", "duration_s": 16, "is_vertical": false, "views": 841}, {"id": "23caXYF8hPQ", "title": "12. Juli 2026", "channel": "Hannelore Knabe", "channel_id": "UCjGPs5r25IyBZdFeNrvGZmg", "thumbnail": "https://i.ytimg.com/vi/23caXYF8hPQ/hqdefault.jpg", "duration_s": 30, "is_vertical": false, "views": 575}, {"id": "bReXdQ8jr4U", "title": "July 12, 2026", "channel": "hh_brothers_uae ", "channel_id": "UClEy_Oyep453iJZH2q12Tiw", "thumbnail": "https://i.ytimg.com/vi/bReXdQ8jr4U/hqdefault.jpg", "duration_s": 17, "is_vertical": false, "views": 1054}, {"id": "qrmWY_7Gn8s", "title": "July 12, 2026", "channel": "One Love Music 🎶 ", "channel_id": "UCSrmLPwAyhrahPPr4QWjnlQ", "thumbnail": "https://i.ytimg.com/vi/qrmWY_7Gn8s/hqdefault.jpg", "duration_s": 46, "is_vertical": false, "views": 421}, {"id": "qPp-agSXfio", "title": "12 July 2026", "channel": "Kuruvankottai Ganesan_Official", "channel_id": "UCaZD8TLO9n6c4tQECVl-wOg", "thumbnail": "https://i.ytimg.com/vi/qPp-agSXfio/hqdefault.jpg", "duration_s": 123, "is_vertical": false, "views": 3827}, {"id": "QLVMX-PbBwA", "title": "🔴LIVE OM LORENSA - BERSIH DESA CELEP KECAMATAN KEDAWUNG - ALFA AUDIO - 35 LIGHTING - AA MEDIA PUSAT", "channel": "AA MULTIMEDIA", "channel_id": "UCIRXFzXJ-uVXfHloTZh83xQ", "thumbnail": "https://i.ytimg.com/vi/QLVMX-PbBwA/hqdefault_live.jpg", "duration_s": 0, "is_vertical": false, "views": 3794}, {"id": "a7aC0uxUUiE", "title": "LIVE MALAM PAGELARAN SANDIWARA DWI WARNA || SEDEKAH LAUT TAHUN 2026 - LOSARI - MINGGU 12 JULI 2026", "channel": "RE MEDIA PRO", "channel_id": "UCGybmFCHTZ9NZjgSnwCsm3g", "thumbnail": "https://i.ytimg.com/vi/a7aC0uxUUiE/hqdefault_live.jpg", "duration_s": 0, "is_vertical": false, "views": 3685}, {"id": "SSKlENaiW80", "title": "[LIVE] Pembacaan Maulid [12 Juli 2026] | Majelis Nurul Amin Samarinda", "channel": "Majelis Ta'lim Nurul Amin Samarinda", "channel_id": "UCOZah6oPXf0G9qYYwN0iNuw", "thumbnail": "https://i.ytimg.com/vi/SSKlENaiW80/hqdefault_live.jpg", "duration_s": 0, "is_vertical": false, "views": 2514}, {"id": "TXY6Z7XIrqI", "title": "12 July 2026", "channel": "mahesh mansiwala ", "channel_id": "UCRGNBRKPdrwc2wXWynmjz9g", "thumbnail": "https://i.ytimg.com/vi/TXY6Z7XIrqI/hqdefault.jpg", "duration_s": 27, "is_vertical": false, "views": 539}, {"id": "07f4c-ZYIlg", "title": "12 Juli 2026", "channel": "animal_hospital_anomaly", "channel_id": "UC-Tl1Etyfofcq2XcFSHuXRg", "thumbnail": "https://i.ytimg.com/vi/07f4c-ZYIlg/hqdefault.jpg", "duration_s": 30, "is_vertical": false, "views": 505}, {"id": "xVKhLNpmi90", "title": "12 Juli 2026", "channel": "MARTHA IMELDA KOLIS", "channel_id": "UCY8rJhlnqp351HQ5suo3nYQ", "thumbnail": "https://i.ytimg.com/vi/xVKhLNpmi90/hqdefault.jpg", "duration_s": 169, "is_vertical": false, "views": 543}, {"id": "QiZ29c_nels", "title": "12. Juli 2026", "channel": "☆Josy☆", "channel_id": "UCEy9h56nzu9AR6Dtplfx_5A", "thumbnail": "https://i.ytimg.com/vi/QiZ29c_nels/hqdefault.jpg", "duration_s": 64, "is_vertical": false, "views": 2235}, {"id": "PzhnYzU8jTo", "title": "Suasana Kebaktian Minggu, 12 Juli 2026 di Graha YHS Balikpapan dipenuhi Penyembahan & Penyembuhan", "channel": "pastor andi simon TV", "channel_id": "UCRWFSYpMbXc8pbk8dQkdd8A", "thumbnail": "https://i.ytimg.com/vi/PzhnYzU8jTo/hqdefault.jpg", "duration_s": 81, "is_vertical": false, "views": 1184}, {"id": "4gDf98Y4QcE", "title": "12 lipca 2026", "channel": "Wlosowero", "channel_id": "UCGy8dGlH3OhQcRyNZl3Sknw", "thumbnail": "https://i.ytimg.com/vi/4gDf98Y4QcE/hqdefault.jpg", "duration_s": 29, "is_vertical": false, "views": 2849}, {"id": "DU11jnQ4XQw", "title": "12 Juli 2026", "channel": "Alvaro Zul", "channel_id": "UCCwEi4D4_n4EN4cq_Ffxv8g", "thumbnail": "https://i.ytimg.com/vi/DU11jnQ4XQw/hqdefault.jpg", "duration_s": 29, "is_vertical": false, "views": 474}, {"id": "S_QzWeFxibM", "title": "12 Juli 2026", "channel": "BANG ⁿººᵇʀεαρεʀ", "channel_id": "UCtvJE4HZT6DYU4hhoM_LU_Q", "thumbnail": "https://i.ytimg.com/vi/S_QzWeFxibM/hqdefault.jpg", "duration_s": 24, "is_vertical": false, "views": 685}, {"id": "_mk-HbUZny0", "title": "12. Juli 2026", "channel": "Die bros", "channel_id": "UC-9AOFaMKyvDP5FZQh39lCQ", "thumbnail": "https://i.ytimg.com/vi/_mk-HbUZny0/hqdefault.jpg", "duration_s": 52, "is_vertical": false, "views": 684}, {"id": "CtWR9hnZdos", "title": "MALAM PUNCAK HARLAH AL-BAHJAH KE-17 | 27 Muharram 1448 H / 12 Juli 2026 M", "channel": "Al-Bahjah TV", "channel_id": "UC50vyjmknAf3nMvOr37gm1Q", "thumbnail": "https://i.ytimg.com/vi/CtWR9hnZdos/hqdefault_live.jpg", "duration_s": 0, "is_vertical": false, "views": 3362}, {"id": "aR3RX-2ZigI", "title": "12. Juli 2026", "channel": "Mr Rice ", "channel_id": "UCdtU7N3U-rS9kKgR0Am5d8w", "thumbnail": "https://i.ytimg.com/vi/aR3RX-2ZigI/hqdefault.jpg", "duration_s": 44, "is_vertical": false, "views": 603}, {"id": "GgO2gb45VL8", "title": "12 July 2026", "channel": "Funny shorts video.05 ", "channel_id": "UC6a_cypaVxvBSbLiYO8xF7Q", "thumbnail": "https://i.ytimg.com/vi/GgO2gb45VL8/hqdefault.jpg", "duration_s": 17, "is_vertical": false, "views": 1796}, {"id": "LDiUt4LaHNk", "title": "12. Juli 2026", "channel": "Hardam", "channel_id": "UCE5mPiG5Bw7-GoUIWT8KZCQ", "thumbnail": "https://i.ytimg.com/vi/LDiUt4LaHNk/hqdefault.jpg", "duration_s": 35, "is_vertical": false, "views": 614}, {"id": "CwRVUYdDMlA", "title": "Pendapatan Daerah Provinsi Jawa Barat 12 Juli 2026", "channel": "Bapenda Jabar", "channel_id": "UC_h_RLcZQBTJWfj8HyMuLeQ", "thumbnail": "https://i.ytimg.com/vi/CwRVUYdDMlA/hqdefault.jpg", "duration_s": 112, "is_vertical": false, "views": 465}, {"id": "TotWTzba3DY", "title": "12 Juli 2026", "channel": "Yoyok Setia", "channel_id": "UCB7ZsjBX9QyeN30kAE0PmWA", "thumbnail": "https://i.ytimg.com/vi/TotWTzba3DY/hqdefault.jpg", "duration_s": 49, "is_vertical": false, "views": 996}, {"id": "_YfogNcLfmk", "title": "July 12, 2026", "channel": "Joel Kahn, MD, Healthy Heart Doc", "channel_id": "UCXWkXL4pzZ_p3o-FbYB4FLw", "thumbnail": "https://i.ytimg.com/vi/_YfogNcLfmk/hqdefault.jpg", "duration_s": 61, "is_vertical": false, "views": 639}, {"id": "RiDZCcBZKCI", "title": "12. Juli 2026", "channel": "Fikaro fire", "channel_id": "UCk4s0F9SPjw_m5zvD6bhVhA", "thumbnail": "https://i.ytimg.com/vi/RiDZCcBZKCI/hqdefault.jpg", "duration_s": 30, "is_vertical": false, "views": 626}, {"id": "LF6fBmgiIyE", "title": "12 Juli 2026", "channel": "Shinbi house_selly!!?", "channel_id": "UCQIcruiiC844xFoWEFKxwFQ", "thumbnail": "https://i.ytimg.com/vi/LF6fBmgiIyE/hqdefault.jpg", "duration_s": 20, "is_vertical": false, "views": 777}, {"id": "7q7qPJkylPk", "title": "12. Juli 2026", "channel": "SKS Selbstverteidigung Kampfkunst Selbstsicherheit", "channel_id": "UCig7GraMAWdbysVqaIgNZNw", "thumbnail": "https://i.ytimg.com/vi/7q7qPJkylPk/hqdefault.jpg", "duration_s": 5, "is_vertical": false, "views": 930}, {"id": "f9Xpm4jngoQ", "title": "12 Juli 2026", "channel": "p★7", "channel_id": "UChk9oAOgvWbBr9rrpi3IREg", "thumbnail": "https://i.ytimg.com/vi/f9Xpm4jngoQ/hqdefault.jpg", "duration_s": 20, "is_vertical": false, "views": 784}, {"id": "yxANOyHCv7s", "title": "12 Juli 2026", "channel": "Adeeva Dan Asha", "channel_id": "UCt-qmWFquID6GI3G4WKiBNA", "thumbnail": "https://i.ytimg.com/vi/yxANOyHCv7s/hqdefault.jpg", "duration_s": 49, "is_vertical": false, "views": 1198}, {"id": "O2xkWgdQYpc", "title": "12 Juli 2026", "channel": "Jihan Sharma Sharma", "channel_id": "UCGKkrqfAPIi3IQkmU65npNQ", "thumbnail": "https://i.ytimg.com/vi/O2xkWgdQYpc/hqdefault.jpg", "duration_s": 83, "is_vertical": false, "views": 526}, {"id": "OwrLYXDc3XU", "title": "12. juli 2026", "channel": "Lene", "channel_id": "UCUGJpRho5l6kz6QyIBvtpug", "thumbnail": "https://i.ytimg.com/vi/OwrLYXDc3XU/hqdefault.jpg", "duration_s": 28, "is_vertical": false, "views": 1053}, {"id": "yY_k4QAa4ZU", "title": "12 Juli 2026", "channel": "Faaris Samlah", "channel_id": "UCEmclMX7g2MHj3my3VTpzyA", "thumbnail": "https://i.ytimg.com/vi/yY_k4QAa4ZU/hqdefault.jpg", "duration_s": 52, "is_vertical": false, "views": 653}, {"id": "xVhhY5G-phE", "title": "12. Juli 2026", "channel": "Bennet Kemper", "channel_id": "UCAtufwrJ0OeReCCKVe4Ul4A", "thumbnail": "https://i.ytimg.com/vi/xVhhY5G-phE/hqdefault.jpg", "duration_s": 85, "is_vertical": false, "views": 266}, {"id": "heocNdMO2jM", "title": "12 July 2026", "channel": "Kingdom", "channel_id": "UCOarl_UuBF_ntQ7nUxCyT4g", "thumbnail": "https://i.ytimg.com/vi/heocNdMO2jM/hqdefault.jpg", "duration_s": 14, "is_vertical": false, "views": 4446}, {"id": "t-qxAKtbUWY", "title": "12 Juli 2026", "channel": "BACRIT TUBE", "channel_id": "UC-UlOaklqD9qNB6V6pKQFYQ", "thumbnail": "https://i.ytimg.com/vi/t-qxAKtbUWY/hqdefault.jpg", "duration_s": 38, "is_vertical": false, "views": 3309}, {"id": "NwO-Bev5slk", "title": "12 Juli 2026", "channel": "Sri - Wahyuni ", "channel_id": "UCUAAV53_ebR7KNz5KqcAEVQ", "thumbnail": "https://i.ytimg.com/vi/NwO-Bev5slk/hqdefault.jpg", "duration_s": 97, "is_vertical": false, "views": 539}, {"id": "nOWMCHN-1Os", "title": "12 Juli 2026", "channel": "maryanti anti", "channel_id": "UCt9NSIGD7cdzfs9YuqCIQrA", "thumbnail": "https://i.ytimg.com/vi/nOWMCHN-1Os/hqdefault.jpg", "duration_s": 29, "is_vertical": false, "views": 1826}, {"id": "RoOg0On1ByQ", "title": "12. Juli 2026", "channel": "Viktorowitsch / Викторович", "channel_id": "UCgLmAD8swybvGpjf45bCwLQ", "thumbnail": "https://i.ytimg.com/vi/RoOg0On1ByQ/hqdefault.jpg", "duration_s": 150, "is_vertical": false, "views": 832}, {"id": "0Z-XMOyIJs0", "title": "12 Juli 2026", "channel": "Izal ink", "channel_id": "UCvLtMZ0gl81zSRPm1eshqnA", "thumbnail": "https://i.ytimg.com/vi/0Z-XMOyIJs0/hqdefault.jpg", "duration_s": 130, "is_vertical": false, "views": 685}, {"id": "yVuVb0hGVlM", "title": "July 12, 2026", "channel": "DANTANA 773", "channel_id": "UCkTmRUjxWU4sfcfHPY3h87Q", "thumbnail": "https://i.ytimg.com/vi/yVuVb0hGVlM/hqdefault.jpg", "duration_s": 73, "is_vertical": false, "views": 1004}, {"id": "ybLoPuOOKmY", "title": "12. Juli 2026", "channel": "Lena Jensen", "channel_id": "UC-uK_BObJujO5sa9mlujgqA", "thumbnail": "https://i.ytimg.com/vi/ybLoPuOOKmY/hqdefault.jpg", "duration_s": 27, "is_vertical": false, "views": 1806}, {"id": "9hYV-8ABcEw", "title": "12 Juli 2026", "channel": "Pendi Penddi", "channel_id": "UCOTMLf9VMyxgM26UP3ULZ_w", "thumbnail": "https://i.ytimg.com/vi/9hYV-8ABcEw/hqdefault.jpg", "duration_s": 57, "is_vertical": false, "views": 493}, {"id": "d_guh69KjK4", "title": "12. Juli 2026", "channel": "Ada Theilken", "channel_id": "UCD262yH3ifZgLmUq-Q087aA", "thumbnail": "https://i.ytimg.com/vi/d_guh69KjK4/hqdefault.jpg", "duration_s": 11, "is_vertical": false, "views": 10603}, {"id": "zV8RJVKnfCM", "title": "12. Juli 2026", "channel": "Givemeyourmoney", "channel_id": "UCnqVta5ER2W7-SwoOAgXQoA", "thumbnail": "https://i.ytimg.com/vi/zV8RJVKnfCM/hqdefault.jpg", "duration_s": 14, "is_vertical": false, "views": 1914}, {"id": "eWQkUcAMeeA", "title": "12. Juli 2026", "channel": "CR79", "channel_id": "UCIcRDQkXSc5g05a4jddUXXQ", "thumbnail": "https://i.ytimg.com/vi/eWQkUcAMeeA/hqdefault.jpg", "duration_s": 13, "is_vertical": false, "views": 789}, {"id": "WJKUwlWbjsM", "title": "12. Juli 2026", "channel": "Iron Mike Biohacking", "channel_id": "UC1zz3I8-PRgF9wASRy0rWKQ", "thumbnail": "https://i.ytimg.com/vi/WJKUwlWbjsM/hqdefault.jpg", "duration_s": 61, "is_vertical": false, "views": 816}, {"id": "w-nzRAk05qA", "title": "12. Juli 2026", "channel": "Katy💯🌹", "channel_id": "UCMBMXLBW0v-MzyKHAnvtpNg", "thumbnail": "https://i.ytimg.com/vi/w-nzRAk05qA/hqdefault.jpg", "duration_s": 33, "is_vertical": false, "views": 739}, {"id": "wpAyQ3X8pR0", "title": "12. Juli 2026", "channel": "Harut Estevao", "channel_id": "UCIdgw-mUAMNxsdnGo-JUKSA", "thumbnail": "https://i.ytimg.com/vi/wpAyQ3X8pR0/hqdefault.jpg", "duration_s": 86, "is_vertical": false, "views": 1067}, {"id": "j13eC8jiXkA", "title": "12. Juli 2026", "channel": "Manuela", "channel_id": "UC7VsBTD2Z37oyCOUd9eaY6A", "thumbnail": "https://i.ytimg.com/vi/j13eC8jiXkA/hqdefault.jpg", "duration_s": 74, "is_vertical": false, "views": 662}, {"id": "b6rvJqiR8mA", "title": "12. Juli 2026", "channel": "Yigit01", "channel_id": "UCSVre-oGTJB6_mE97AhQ_9A", "thumbnail": "https://i.ytimg.com/vi/b6rvJqiR8mA/hqdefault.jpg", "duration_s": 16, "is_vertical": false, "views": 916}, {"id": "xOH2358QZEA", "title": "12. Juli 2026", "channel": "RobloxFan8372", "channel_id": "UC5aUebq7RXY_q9L4AoWGeMg", "thumbnail": "https://i.ytimg.com/vi/xOH2358QZEA/hqdefault.jpg", "duration_s": 22, "is_vertical": false, "views": 922}, {"id": "j6koSnQhf8A", "title": "12. Juli 2026", "channel": "Collin", "channel_id": "UCwIUO7ymRtmsE6PWw_lpsBg", "thumbnail": "https://i.ytimg.com/vi/j6koSnQhf8A/hqdefault.jpg", "duration_s": 40, "is_vertical": false, "views": 831}, {"id": "fxEaBYhpmf8", "title": "12 Juli 2026", "channel": "BERITA TERBARU ", "channel_id": "UC_MhfoU4q_8ykfhQynpH6eA", "thumbnail": "https://i.ytimg.com/vi/fxEaBYhpmf8/hqdefault.jpg", "duration_s": 6, "is_vertical": false, "views": 39530}, {"id": "B-XjDZvJX_k", "title": "12. Juli 2026", "channel": "Galinas Welt: Вязание и летние маршруты", "channel_id": "UCufhq1Wz9UYXZKHqbOazYyg", "thumbnail": "https://i.ytimg.com/vi/B-XjDZvJX_k/hqdefault.jpg", "duration_s": 29, "is_vertical": false, "views": 685}, {"id": "sEE-YuhvqvA", "title": "12 Juli 2026", "channel": "BERITA TERBARU ", "channel_id": "UC_MhfoU4q_8ykfhQynpH6eA", "thumbnail": "https://i.ytimg.com/vi/sEE-YuhvqvA/hqdefault.jpg", "duration_s": 6, "is_vertical": false, "views": 31575}, {"id": "zwqVokdqxXI", "title": "12. Juli 2026", "channel": "andy helf", "channel_id": "UCsyd6FUFw7u480NLzEqykQA", "thumbnail": "https://i.ytimg.com/vi/zwqVokdqxXI/hqdefault.jpg", "duration_s": 52, "is_vertical": false, "views": 982}, {"id": "tbhz57TErzE", "title": "12. Juli 2026", "channel": "green apple", "channel_id": "UC_8JWZ9pwfmo970px-9Dw7A", "thumbnail": "https://i.ytimg.com/vi/tbhz57TErzE/hqdefault.jpg", "duration_s": 16, "is_vertical": false, "views": 1535}, {"id": "51zhiqL5n8Y", "title": "12. Juli 2026", "channel": "@ Lara 12", "channel_id": "UCv19umYkrUjQKfkHbtE_lWw", "thumbnail": "https://i.ytimg.com/vi/51zhiqL5n8Y/hqdefault.jpg", "duration_s": 29, "is_vertical": false, "views": 1492}, {"id": "mLxETj1H0vk", "title": "12. Juli 2026", "channel": "Noor _cool😊", "channel_id": "UCoW5YvaDYC6WHGqM8qk7THQ", "thumbnail": "https://i.ytimg.com/vi/mLxETj1H0vk/hqdefault.jpg", "duration_s": 7, "is_vertical": false, "views": 6700}, {"id": "rqhf--DOJXs", "title": "12. Juli 2026", "channel": "Die King of Pub", "channel_id": "UCwjamfpBFliXY3O-CpS1ANg", "thumbnail": "https://i.ytimg.com/vi/rqhf--DOJXs/hqdefault.jpg", "duration_s": 16, "is_vertical": false, "views": 1192}, {"id": "R_kpKm7jNaE", "title": "12. Juli 2026", "channel": "Lauin ", "channel_id": "UC7nCiMGWk83JXRuK8oV4J7w", "thumbnail": "https://i.ytimg.com/vi/R_kpKm7jNaE/hqdefault.jpg", "duration_s": 31, "is_vertical": false, "views": 839}, {"id": "gE2sMVvGmS4", "title": "12. Juli 2026", "channel": "Landwirtschaft-ottendorf-sh ", "channel_id": "UCOtcrda1PYLIT-tikP6S9-Q", "thumbnail": "https://i.ytimg.com/vi/gE2sMVvGmS4/hqdefault.jpg", "duration_s": 12, "is_vertical": false, "views": 1738}, {"id": "oEHNsU6uDN0", "title": "✨HARGA BELI EMAS 12 Juli 2026 #jualemas #emas #tokomaslia", "channel": "Toko Mas LIA Bekasi", "channel_id": "UCusy3R0VpHAr02Aeot8MfHA", "thumbnail": "https://i.ytimg.com/vi/oEHNsU6uDN0/hqdefault.jpg", "duration_s": 45, "is_vertical": false, "views": 2274}, {"id": "3OsVbhq7agc", "title": "12. Juli 2026", "channel": "Lukas und Devin", "channel_id": "UCSq4dPI7iFO4dtX0UEmUsPw", "thumbnail": "https://i.ytimg.com/vi/3OsVbhq7agc/hqdefault.jpg", "duration_s": 16, "is_vertical": false, "views": 1330}, {"id": "yMjCFd_Kgi0", "title": "12 Juli 2026", "channel": "∆ Spongebob ×", "channel_id": "UCp1HxXQh_SxvPWnToKZHDtQ", "thumbnail": "https://i.ytimg.com/vi/yMjCFd_Kgi0/hqdefault.jpg", "duration_s": 15, "is_vertical": false, "views": 1208}, {"id": "EjDQhdPjkWg", "title": "12. Juli 2026", "channel": "FrTV", "channel_id": "UC_dviW26fkmuP32yxTmzR7g", "thumbnail": "https://i.ytimg.com/vi/EjDQhdPjkWg/hqdefault.jpg", "duration_s": 16, "is_vertical": false, "views": 966}, {"id": "Odx2q48bRQA", "title": "12. Juli 2026", "channel": "Leo", "channel_id": "UCkL4DpNkzkIXAVrau05jWTg", "thumbnail": "https://i.ytimg.com/vi/Odx2q48bRQA/hqdefault.jpg", "duration_s": 13, "is_vertical": false, "views": 1336}, {"id": "NI2GGanf_cI", "title": "12. Juli 2026", "channel": "mado und lilly ", "channel_id": "UC0TNyHQAsBNdOTcI5u9NkdA", "thumbnail": "https://i.ytimg.com/vi/NI2GGanf_cI/hqdefault.jpg", "duration_s": 16, "is_vertical": false, "views": 1383}, {"id": "EfVJ0R83uis", "title": "Trust kommt böse 😋", "channel": "Chris", "channel_id": "UCY450UvVpYd4LIcCFoSXPGw", "thumbnail": "https://i.ytimg.com/vi/EfVJ0R83uis/hqdefault.jpg", "duration_s": 37, "is_vertical": false, "views": 1110}, {"id": "1afoKsibGi4", "title": "12. Juli 2026", "channel": "Marcel ", "channel_id": "UCHCu2Nl148AIGnRLMp1xSiw", "thumbnail": "https://i.ytimg.com/vi/1afoKsibGi4/hqdefault.jpg", "duration_s": 23, "is_vertical": false, "views": 984}, {"id": "Rm3xDZ01o8Y", "title": "12. Juli 2026", "channel": "Ronaldinho", "channel_id": "UCTR4DEt-jIm8zLuP-D-R0cA", "thumbnail": "https://i.ytimg.com/vi/Rm3xDZ01o8Y/hqdefault.jpg", "duration_s": 18, "is_vertical": false, "views": 1377}, {"id": "Sz2zgBBASH8", "title": "12. Juli 2026", "channel": "MABE", "channel_id": "UC51ksw4dQ81fraNtcRGmA8A", "thumbnail": "https://i.ytimg.com/vi/Sz2zgBBASH8/hqdefault.jpg", "duration_s": 25, "is_vertical": false, "views": 1699}, {"id": "m0MNI1-OIeM", "title": "12. Juli 2026", "channel": "ClaraXFriends", "channel_id": "UC9esk4hotWZF3kPpvOhh9EA", "thumbnail": "https://i.ytimg.com/vi/m0MNI1-OIeM/hqdefault.jpg", "duration_s": 11, "is_vertical": false, "views": 1670}, {"id": "ILHI3Lz2U-U", "title": "12 Juli 2026", "channel": "H&H Skincare Official", "channel_id": "UCmzVx0wvvp4t8oRoXV9AQyg", "thumbnail": "https://i.ytimg.com/vi/ILHI3Lz2U-U/hqdefault.jpg", "duration_s": 39, "is_vertical": false, "views": 1230}, {"id": "Wcv8cZNwmZA", "title": "12. Juli 2026", "channel": "IkobYT ", "channel_id": "UCFmtByTURfhqrB-zJnDr6Vw", "thumbnail": "https://i.ytimg.com/vi/Wcv8cZNwmZA/hqdefault.jpg", "duration_s": 16, "is_vertical": false, "views": 1066}, {"id": "HILx5_eTqhY", "title": "12. Juli 2026", "channel": "Miri", "channel_id": "UCMJtfOjBlIvDywdnHAxg1jQ", "thumbnail": "https://i.ytimg.com/vi/HILx5_eTqhY/hqdefault.jpg", "duration_s": 7, "is_vertical": false, "views": 2443}, {"id": "bkLuYfD5fWA", "title": "12. Juli 2026", "channel": "JBSO🇦🇫", "channel_id": "UCdj1IlKafGUV37kMELyMhNw", "thumbnail": "https://i.ytimg.com/vi/bkLuYfD5fWA/hqdefault.jpg", "duration_s": 27, "is_vertical": false, "views": 694}, {"id": "dYwljr_41gg", "title": "12. Juli 2026", "channel": "Sam Mirzaeigorani ", "channel_id": "UCi7Tx8pLpatwf8FijiwFMgA", "thumbnail": "https://i.ytimg.com/vi/dYwljr_41gg/hqdefault.jpg", "duration_s": 32, "is_vertical": false, "views": 956}, {"id": "P_8bhmzF3r4", "title": "12. Juli 2026", "channel": " ST4R ", "channel_id": "UC4MgBZp5XlZr1V5NWS_9oeg", "thumbnail": "https://i.ytimg.com/vi/P_8bhmzF3r4/hqdefault.jpg", "duration_s": 16, "is_vertical": false, "views": 1387}, {"id": "f6YxdOHKETc", "title": "12. Juli 2026", "channel": "Gabi N.", "channel_id": "UCX703QnnVshx3rlhjPsT7Jg", "thumbnail": "https://i.ytimg.com/vi/f6YxdOHKETc/hqdefault.jpg", "duration_s": 24, "is_vertical": false, "views": 6615}, {"id": "q2PZ_Vnt7o0", "title": "BUYBACK EMAS TERTINGGI 12 Juli 2026 #jualemas #emas", "channel": "Toko Mas LIA Bekasi", "channel_id": "UCusy3R0VpHAr02Aeot8MfHA", "thumbnail": "https://i.ytimg.com/vi/q2PZ_Vnt7o0/hqdefault.jpg", "duration_s": 27, "is_vertical": false, "views": 2301}, {"id": "BKLcghMkjdQ", "title": "12 Juli 2026", "channel": "black_2972", "channel_id": "UC7XCb-8_0XkStn7Hh0ZZjDg", "thumbnail": "https://i.ytimg.com/vi/BKLcghMkjdQ/hqdefault.jpg", "duration_s": 6, "is_vertical": false, "views": 1652}, {"id": "k3UnjlMzmLI", "title": "12. Juli 2026", "channel": "GoofyColatrinker", "channel_id": "UCpr3tCCIAmVD7NXPmiHg1wg", "thumbnail": "https://i.ytimg.com/vi/k3UnjlMzmLI/hqdefault.jpg", "duration_s": 34, "is_vertical": false, "views": 1009}, {"id": "mRJZmtuYT5Q", "title": "12 Juli 2026", "channel": "farojan943", "channel_id": "UCaj7VXNeltIp701q3ELOGOA", "thumbnail": "https://i.ytimg.com/vi/mRJZmtuYT5Q/hqdefault.jpg", "duration_s": 15, "is_vertical": false, "views": 1204}, {"id": "tueUE7LOqgo", "title": "12. Juli 2026", "channel": "micha", "channel_id": "UCrPOLN-WrP9FygW9tMx3T0w", "thumbnail": "https://i.ytimg.com/vi/tueUE7LOqgo/hqdefault.jpg", "duration_s": 40, "is_vertical": false, "views": 1089}, {"id": "UJs3mf7AEfQ", "title": "12. Juli 2026", "channel": "Luna und Lea", "channel_id": "UCPNT3iuJxf1I2O97a9xnmIw", "thumbnail": "https://i.ytimg.com/vi/UJs3mf7AEfQ/hqdefault.jpg", "duration_s": 20, "is_vertical": false, "views": 1478}, {"id": "IR41AoUFiR0", "title": "12. Juli 2026", "channel": "123B&J321", "channel_id": "UCQaZUbxOqhOXxPhypheN9dA", "thumbnail": "https://i.ytimg.com/vi/IR41AoUFiR0/hqdefault.jpg", "duration_s": 13, "is_vertical": false, "views": 1070}, {"id": "UROcSMhQcrM", "title": "12. Juli 2026", "channel": "cookie Dough ", "channel_id": "UC4aQq9yk9ugqwk4x-0XKK-w", "thumbnail": "https://i.ytimg.com/vi/UROcSMhQcrM/hqdefault.jpg", "duration_s": 7, "is_vertical": false, "views": 1391}, {"id": "Fk9NuoKnCBE", "title": "12. Juli 2026", "channel": "Ronaldo_pro", "channel_id": "UC21I6wAVeCq-6QS4ifKVF7A", "thumbnail": "https://i.ytimg.com/vi/Fk9NuoKnCBE/hqdefault.jpg", "duration_s": 26, "is_vertical": false, "views": 1083}, {"id": "zNdTEFeT8WE", "title": "12. Juli 2026", "channel": "Bmx-Mtb", "channel_id": "UCXY5VdZEUApC0xX6ow9QdlQ", "thumbnail": "https://i.ytimg.com/vi/zNdTEFeT8WE/hqdefault.jpg", "duration_s": 61, "is_vertical": false, "views": 327}, {"id": "TU-RAkGuOXc", "title": "12. Juli 2026", "channel": "Bmx-Mtb", "channel_id": "UCXY5VdZEUApC0xX6ow9QdlQ", "thumbnail": "https://i.ytimg.com/vi/TU-RAkGuOXc/hqdefault.jpg", "duration_s": 61, "is_vertical": false, "views": 601}, {"id": "sdWA6FnBojg", "title": "12 Juli 2026", "channel": "chenel boy 12", "channel_id": "UCobA2e5Eog8lkPgdnZegCEQ", "thumbnail": "https://i.ytimg.com/vi/sdWA6FnBojg/hqdefault.jpg", "duration_s": 10, "is_vertical": false, "views": 1583}, {"id": "GvJd5HVrssw", "title": "12 Juli 2026", "channel": "BRIAN GARREN OFFICIAL ", "channel_id": "UCX9v-NghG11v4BTAE6piSig", "thumbnail": "https://i.ytimg.com/vi/GvJd5HVrssw/hqdefault.jpg", "duration_s": 17, "is_vertical": false, "views": 1323}, {"id": "f50l7PgslyY", "title": "12. Juli 2026", "channel": "Sophie", "channel_id": "UCYZqawA-wGIUhIYIdIwOI8w", "thumbnail": "https://i.ytimg.com/vi/f50l7PgslyY/hqdefault.jpg", "duration_s": 11, "is_vertical": false, "views": 1067}, {"id": "69c_KnSIY2w", "title": "12 июля 2026 г.", "channel": "irik511 fan TAEKOOK ", "channel_id": "UC8xWz53TmN2xlRl8OM1lQ8A", "thumbnail": "https://i.ytimg.com/vi/69c_KnSIY2w/hqdefault.jpg", "duration_s": 118, "is_vertical": false, "views": 28755}, {"id": "_bieNHaTIlU", "title": "12. Juli 2026", "channel": "Evgens Activity Channel", "channel_id": "UCYUX1d1lWLUOiaPzOWXKfoA", "thumbnail": "https://i.ytimg.com/vi/_bieNHaTIlU/hqdefault.jpg", "duration_s": 56, "is_vertical": false, "views": 958}, {"id": "8ZRpyIpGpvc", "title": "12. Juli 2026", "channel": "andy_roblox", "channel_id": "UCUz5WFBwGfBx6DpckSJpc7Q", "thumbnail": "https://i.ytimg.com/vi/8ZRpyIpGpvc/hqdefault.jpg", "duration_s": 24, "is_vertical": false, "views": 843}, {"id": "Ez7K1seH1vo", "title": "12. Juli 2026", "channel": "DXRacer", "channel_id": "UCdcFXuyUMLNFHiISCD5mlJA", "thumbnail": "https://i.ytimg.com/vi/Ez7K1seH1vo/hqdefault.jpg", "duration_s": 9, "is_vertical": false, "views": 1610}, {"id": "9I_AjPg_UTk", "title": "12 luglio 2026", "channel": "DRILON LUGJA", "channel_id": "UCTkW7E8aYJAHRwrza0zQdLA", "thumbnail": "https://i.ytimg.com/vi/9I_AjPg_UTk/hqdefault.jpg", "duration_s": 27, "is_vertical": false, "views": 24993}, {"id": "xxfaghvVkqE", "title": "12 Juli 2026", "channel": "Basuki Suwarno", "channel_id": "UCF1PACdx2ar_mvt84bbITjQ", "thumbnail": "https://i.ytimg.com/vi/xxfaghvVkqE/hqdefault.jpg", "duration_s": 38, "is_vertical": false, "views": 17227}, {"id": "tdNz5y7Ijr0", "title": "12. Juli 2026", "channel": "elias", "channel_id": "UCWzq8RtacgJ_LR5ZM4bgwuQ", "thumbnail": "https://i.ytimg.com/vi/tdNz5y7Ijr0/hqdefault.jpg", "duration_s": 32, "is_vertical": false, "views": 673}, {"id": "iLJ5WDh0Jl4", "title": "12. Juli 2026", "channel": "123B&J321", "channel_id": "UCQaZUbxOqhOXxPhypheN9dA", "thumbnail": "https://i.ytimg.com/vi/iLJ5WDh0Jl4/hqdefault.jpg", "duration_s": 25, "is_vertical": false, "views": 993}, {"id": "C12WQxqkzDg", "title": "12. Juli 2026", "channel": "Arbeitnehmerforum", "channel_id": "UCi2tOAtdS6TEwHQRWK-xSIg", "thumbnail": "https://i.ytimg.com/vi/C12WQxqkzDg/hqdefault.jpg", "duration_s": 97, "is_vertical": false, "views": 553}, {"id": "WYx0j7jfbxU", "title": "12 июля 2026 г.", "channel": "Yulduz 419-magazin", "channel_id": "UCf_BLNdh_VKxZKboE9cI6_g", "thumbnail": "https://i.ytimg.com/vi/WYx0j7jfbxU/hqdefault.jpg", "duration_s": 15, "is_vertical": false, "views": 13303}, {"id": "8cbeDrVFApI", "title": "12 Juli 2026", "channel": "Radja is fierce", "channel_id": "UCVGPq_BuwHtTqyUs2ThtDJQ", "thumbnail": "https://i.ytimg.com/vi/8cbeDrVFApI/hqdefault.jpg", "duration_s": 37, "is_vertical": false, "views": 7689}, {"id": "d_c1M3n2XQE", "title": "12. Juli 2026", "channel": "Vitality422 ", "channel_id": "UCHiFbS1elQcvAolipq1P-EA", "thumbnail": "https://i.ytimg.com/vi/d_c1M3n2XQE/hqdefault.jpg", "duration_s": 61, "is_vertical": false, "views": 1014}, {"id": "Laaubh3D_bs", "title": "12 Juli 2026", "channel": "Dio comonity", "channel_id": "UCG4d31-fXseiQUmzQxYw-KA", "thumbnail": "https://i.ytimg.com/vi/Laaubh3D_bs/hqdefault.jpg", "duration_s": 21, "is_vertical": false, "views": 6876}, {"id": "OkFoBe1-cAM", "title": "12 July 2026", "channel": "Chef Cristian Fratieanu", "channel_id": "UCnngAPRd_PLjZmHAl52ZelA", "thumbnail": "https://i.ytimg.com/vi/OkFoBe1-cAM/hqdefault.jpg", "duration_s": 33, "is_vertical": false, "views": 7985}, {"id": "AJv8A4ESZAI", "title": "12. Juli 2026", "channel": "Cleangirl", "channel_id": "UC2he8jvM4GTUVUVoKxfmnUQ", "thumbnail": "https://i.ytimg.com/vi/AJv8A4ESZAI/hqdefault.jpg", "duration_s": 12, "is_vertical": false, "views": 1298}, {"id": "dLWwcz__1Y4", "title": "12 Juli 2026", "channel": "SaluraN Q", "channel_id": "UC8tKHIhQVL7Rz6N5q_SsOCA", "thumbnail": "https://i.ytimg.com/vi/dLWwcz__1Y4/hqdefault.jpg", "duration_s": 6, "is_vertical": false, "views": 1940}, {"id": "6C4Tm4zGf5o", "title": "12. Juli 2026", "channel": "Sabrina ", "channel_id": "UCxOLu7yNDaK-g9oHGPUTsvQ", "thumbnail": "https://i.ytimg.com/vi/6C4Tm4zGf5o/hqdefault.jpg", "duration_s": 38, "is_vertical": false, "views": 864}, {"id": "PmquxgVJTjE", "title": "12. Juli 2026", "channel": "xxLorenzo7xx", "channel_id": "UCcbxi3pn7FLjVta6_WB3LjA", "thumbnail": "https://i.ytimg.com/vi/PmquxgVJTjE/hqdefault.jpg", "duration_s": 25, "is_vertical": false, "views": 1726}, {"id": "znuyxZPDuyg", "title": "12. Juli 2026", "channel": "Vitality422 ", "channel_id": "UCHiFbS1elQcvAolipq1P-EA", "thumbnail": "https://i.ytimg.com/vi/znuyxZPDuyg/hqdefault.jpg", "duration_s": 20, "is_vertical": false, "views": 1800}, {"id": "JS3AwYRk0t0", "title": "12. Juli 2026", "channel": "DieBellies", "channel_id": "UCZ5ds6yGkI5iBNI2LvrHBrg", "thumbnail": "https://i.ytimg.com/vi/JS3AwYRk0t0/hqdefault.jpg", "duration_s": 21, "is_vertical": false, "views": 1370}, {"id": "ht4c6DcxRmo", "title": "12. Juli 2026", "channel": "Manuela", "channel_id": "UC7VsBTD2Z37oyCOUd9eaY6A", "thumbnail": "https://i.ytimg.com/vi/ht4c6DcxRmo/hqdefault.jpg", "duration_s": 30, "is_vertical": false, "views": 1196}, {"id": "94b-HkPsuK0", "title": "12. Juli 2026", "channel": "Manuela", "channel_id": "UC7VsBTD2Z37oyCOUd9eaY6A", "thumbnail": "https://i.ytimg.com/vi/94b-HkPsuK0/hqdefault.jpg", "duration_s": 99, "is_vertical": false, "views": 658}, {"id": "zpKKd9zqOIE", "title": "12. Juli 2026", "channel": "Josh‘sports", "channel_id": "UCXHWVI-rzPX8VkKPUrbVrkg", "thumbnail": "https://i.ytimg.com/vi/zpKKd9zqOIE/hqdefault.jpg", "duration_s": 10, "is_vertical": false, "views": 1845}, {"id": "8JZbETisrM8", "title": "12 Juli 2026", "channel": "Muedaditya_Official", "channel_id": "UC0Qr14BUxQl3cUtDTOVPMIA", "thumbnail": "https://i.ytimg.com/vi/8JZbETisrM8/hqdefault.jpg", "duration_s": 43, "is_vertical": false, "views": 7902}, {"id": "lDS1DoRDLag", "title": "12 Juli 2026", "channel": "Althaf's Channel ", "channel_id": "UCkdhROkaLgCiyu5i753WGwQ", "thumbnail": "https://i.ytimg.com/vi/lDS1DoRDLag/hqdefault.jpg", "duration_s": 20, "is_vertical": false, "views": 990}, {"id": "AhEfdXqojm8", "title": "12 Juli 2026", "channel": "Watashi Acel", "channel_id": "UCh1bvoQN4LTr4Z120DjRw7A", "thumbnail": "https://i.ytimg.com/vi/AhEfdXqojm8/hqdefault.jpg", "duration_s": 74, "is_vertical": false, "views": 1349}, {"id": "O6lZSGoOwYE", "title": "12 Juli 2026", "channel": "Ami 123", "channel_id": "UCMAj2jzPo7rtYwVZfTZYyNg", "thumbnail": "https://i.ytimg.com/vi/O6lZSGoOwYE/hqdefault.jpg", "duration_s": 11, "is_vertical": false, "views": 1502}, {"id": "W48nfdF1gFE", "title": "12. Juli 2026", "channel": "Faris007", "channel_id": "UCyc74dCTgiolmFZxZhKyKMw", "thumbnail": "https://i.ytimg.com/vi/W48nfdF1gFE/hqdefault.jpg", "duration_s": 40, "is_vertical": false, "views": 1892}, {"id": "FH1RH7KDhcw", "title": "12 Juli 2026", "channel": "@Alby_official29#", "channel_id": "UC95LYrVr4z4JMLW4CrOjkDw", "thumbnail": "https://i.ytimg.com/vi/FH1RH7KDhcw/hqdefault.jpg", "duration_s": 15, "is_vertical": false, "views": 5276}, {"id": "6hR64FKSuwY", "title": "12 Juli 2026", "channel": "yusuf ", "channel_id": "UCkK--GPUpmh-wymlA0Bbo3g", "thumbnail": "https://i.ytimg.com/vi/6hR64FKSuwY/hqdefault.jpg", "duration_s": 16, "is_vertical": false, "views": 1450}, {"id": "U7BsKY85dCM", "title": "12 Juli 2026", "channel": "Mrf Ardiafif", "channel_id": "UCcDkzc1jwEv5RfVGdG85Pxw", "thumbnail": "https://i.ytimg.com/vi/U7BsKY85dCM/hqdefault.jpg", "duration_s": 10, "is_vertical": false, "views": 3097}, {"id": "k1CyxvoMsvg", "title": "12. Juli 2026", "channel": "Alexander Kimm ", "channel_id": "UCAjCrDRaBFIAJt0I22EKmMg", "thumbnail": "https://i.ytimg.com/vi/k1CyxvoMsvg/hqdefault.jpg", "duration_s": 39, "is_vertical": false, "views": 1099}, {"id": "a5teeg1Npx4", "title": "12 Juli 2026", "channel": "bocil mykonos", "channel_id": "UCcOJctQ37Vy2dIwPjbceSmQ", "thumbnail": "https://i.ytimg.com/vi/a5teeg1Npx4/hqdefault.jpg", "duration_s": 18, "is_vertical": false, "views": 1168}, {"id": "CQqzLUsHm6c", "title": "12 июля 2026 г.", "channel": "ЭЛДИК ВИДЕО", "channel_id": "UCpNhKq9Gb7eIMMeJGhILQog", "thumbnail": "https://i.ytimg.com/vi/CQqzLUsHm6c/hqdefault.jpg", "duration_s": 23, "is_vertical": false, "views": 53176}, {"id": "Q2MkPv7NMtI", "title": "12 Juli 2026", "channel": "Kentertainment", "channel_id": "UCeFaaSYoTDxg7LRmiTisEHQ", "thumbnail": "https://i.ytimg.com/vi/Q2MkPv7NMtI/hqdefault.jpg", "duration_s": 8, "is_vertical": false, "views": 7446}, {"id": "ZJaXCDfh8nM", "title": "12 Juli 2026", "channel": "@★SWEET_NAYYA★", "channel_id": "UCn-FyDGf7SOVZUBip3tRriw", "thumbnail": "https://i.ytimg.com/vi/ZJaXCDfh8nM/hqdefault.jpg", "duration_s": 15, "is_vertical": false, "views": 62052}, {"id": "q65GBDd5D2I", "title": "Tagessegen am 12. Juli 2026", "channel": "radio horeb", "channel_id": "UCyIQu6rB26bBxb5BDHhgGMg", "thumbnail": "https://i.ytimg.com/vi/q65GBDd5D2I/hqdefault.jpg", "duration_s": 67, "is_vertical": false, "views": 793}, {"id": "6kk6PIQUUow", "title": "12 Juli 2026", "channel": "motor keren5637", "channel_id": "UCY-9lJ4hqQR61FFS4X1y52w", "thumbnail": "https://i.ytimg.com/vi/6kk6PIQUUow/hqdefault.jpg", "duration_s": 15, "is_vertical": false, "views": 2374}, {"id": "6TrCYT9DQNw", "title": "12 Juli 2026", "channel": "Imam & Nara Official", "channel_id": "UCJ936bXXzI74K-505etxnFw", "thumbnail": "https://i.ytimg.com/vi/6TrCYT9DQNw/hqdefault.jpg", "duration_s": 6, "is_vertical": false, "views": 1837}, {"id": "KCAk0N4v1us", "title": "12. Juli 2026", "channel": "Daniel Dan", "channel_id": "UCXzjzb48TdGzg0ciFL2aJJg", "thumbnail": "https://i.ytimg.com/vi/KCAk0N4v1us/hqdefault.jpg", "duration_s": 33, "is_vertical": false, "views": 283}, {"id": "5JHrH6oO0wk", "title": "July 12, 2026", "channel": "Demerited", "channel_id": "UCDLPU-w7SHHeOk_d0UOyDjw", "thumbnail": "https://i.ytimg.com/vi/5JHrH6oO0wk/hqdefault.jpg", "duration_s": 60, "is_vertical": false, "views": 403}, {"id": "bW0V-h1fQcA", "title": "12. Juli 2026", "channel": "Broski123", "channel_id": "UCoTHbH0WuDfVePZeMpYu6ag", "thumbnail": "https://i.ytimg.com/vi/bW0V-h1fQcA/hqdefault.jpg", "duration_s": 54, "is_vertical": false, "views": 495}, {"id": "uUXY-eonABs", "title": "July 12, 2026", "channel": "EJACK4SHORT", "channel_id": "UCqSLwJN6qr1_WWRb9OZ1gTQ", "thumbnail": "https://i.ytimg.com/vi/uUXY-eonABs/hqdefault.jpg", "duration_s": 31, "is_vertical": false, "views": 402}, {"id": "pJ8nE7QMHSg", "title": "July 12, 2026", "channel": "Marleny1", "channel_id": "UC--M3nYFnlTuw08N52p-yiA", "thumbnail": "https://i.ytimg.com/vi/pJ8nE7QMHSg/hqdefault.jpg", "duration_s": 7, "is_vertical": false, "views": 1721}, {"id": "a41N96QyaF0", "title": "July 12, 2026", "channel": "Skibidi Unc", "channel_id": "UCEq3IILMCHj5OuH3pdGk5yA", "thumbnail": "https://i.ytimg.com/vi/a41N96QyaF0/hqdefault.jpg", "duration_s": 45, "is_vertical": false, "views": 729}, {"id": "CQCC3IJNzko", "title": "12. Juli 2026", "channel": "Anne Wünsche", "channel_id": "UCbqWw1qXVof3XqBuOWi2kjA", "thumbnail": "https://i.ytimg.com/vi/CQCC3IJNzko/hqdefault.jpg", "duration_s": 62, "is_vertical": false, "views": 2195}, {"id": "mZ5CVpUxw1c", "title": "12. Juli 2026", "channel": "sakhi", "channel_id": "UCBL3gFMAoXSJ-JvSjjfEt7w", "thumbnail": "https://i.ytimg.com/vi/mZ5CVpUxw1c/hqdefault.jpg", "duration_s": 25, "is_vertical": false, "views": 633}, {"id": "z5b9-waaywU", "title": "July 12, 2026", "channel": "Ochidi Videos ", "channel_id": "UC2DFeylYqjBrgZCrGDjQOsw", "thumbnail": "https://i.ytimg.com/vi/z5b9-waaywU/hqdefault.jpg", "duration_s": 180, "is_vertical": false, "views": 2513}, {"id": "IhvtY1TL_IY", "title": "July 12, 2026", "channel": "MandatoryFunDay", "channel_id": "UCq_IooL5-mnPOXnjxxfRMrA", "thumbnail": "https://i.ytimg.com/vi/IhvtY1TL_IY/hqdefault.jpg", "duration_s": 47, "is_vertical": false, "views": 1010}, {"id": "87Enbry4jT4", "title": "July 12, 2026", "channel": "Sandra Perez", "channel_id": "UCzQFBG_aGXkxgIqXqOTHpyQ", "thumbnail": "https://i.ytimg.com/vi/87Enbry4jT4/hqdefault.jpg", "duration_s": 153, "is_vertical": false, "views": 1909}, {"id": "S2JIp0IeV0s", "title": "12. Juli 2026", "channel": "𝔹𝕖𝕥𝕙𝕖𝕝 𝕝𝕚𝕖𝕓𝕥 𝕔𝕠𝕠𝕜𝕚𝕖𝕤", "channel_id": "UCx8sMZSL2XfYAXxiGCw_pxA", "thumbnail": "https://i.ytimg.com/vi/S2JIp0IeV0s/hqdefault.jpg", "duration_s": 40, "is_vertical": false, "views": 561}, {"id": "48I3DoNiN9Q", "title": "July 12, 2026", "channel": "BROOKE HYLAND", "channel_id": "UCQaGt6_3JSwM6mhTTQOTfrw", "thumbnail": "https://i.ytimg.com/vi/48I3DoNiN9Q/hqdefault.jpg", "duration_s": 40, "is_vertical": false, "views": 1604}, {"id": "Pfk_hhZRk-s", "title": "July 12, 2026", "channel": "The Rex Watches NYC", "channel_id": "UCXGX0MjiVCSUGVmGIK9sVwA", "thumbnail": "https://i.ytimg.com/vi/Pfk_hhZRk-s/hqdefault.jpg", "duration_s": 172, "is_vertical": false, "views": 1641}, {"id": "McjeD8vktkg", "title": "12. Juli 2026", "channel": "Marcel Hertz", "channel_id": "UC3bLQxxuvQB93b3o-G9--Wg", "thumbnail": "https://i.ytimg.com/vi/McjeD8vktkg/hqdefault.jpg", "duration_s": 42, "is_vertical": false, "views": 1393}, {"id": "WZIUWmAJ0eM", "title": "12 July 2026", "channel": "ABIS_FULANI", "channel_id": "UCQHcdYywVCXTjgSUPZkAPCQ", "thumbnail": "https://i.ytimg.com/vi/WZIUWmAJ0eM/hqdefault.jpg", "duration_s": 137, "is_vertical": false, "views": 3618}, {"id": "134at8JHKzQ", "title": "July 12, 2026", "channel": "Tommy Wind", "channel_id": "UCapc4_nqWVp_0JRpT9EvufQ", "thumbnail": "https://i.ytimg.com/vi/134at8JHKzQ/hqdefault.jpg", "duration_s": 90, "is_vertical": false, "views": 2314}, {"id": "IwAM64uCoZ4", "title": "July 12, 2026", "channel": "Tote & Luxe Co.", "channel_id": "UCJ7pPmeUASgx3MYOTMPTGCA", "thumbnail": "https://i.ytimg.com/vi/IwAM64uCoZ4/hqdefault.jpg", "duration_s": 21, "is_vertical": false, "views": 1520}, {"id": "4rftlTU-zho", "title": "July 12, 2026", "channel": "Prince Agbaeze", "channel_id": "UCBKZPLgKbVevKJHzm5b2Whg", "thumbnail": "https://i.ytimg.com/vi/4rftlTU-zho/hqdefault.jpg", "duration_s": 61, "is_vertical": false, "views": 831}, {"id": "OUK9_iW7FEE", "title": "12. Juli 2026", "channel": "Salko Juklo Official", "channel_id": "UCs8rYJjYeBJH4WPjw7L8lEA", "thumbnail": "https://i.ytimg.com/vi/OUK9_iW7FEE/hqdefault.jpg", "duration_s": 62, "is_vertical": false, "views": 3981}, {"id": "yIm43nq5Keo", "title": "12. Juli 2026", "channel": "Salko Juklo Deutsch", "channel_id": "UCSqQVTBu0qnFGV4_KM-NDXw", "thumbnail": "https://i.ytimg.com/vi/yIm43nq5Keo/hqdefault.jpg", "duration_s": 67, "is_vertical": false, "views": 3880}, {"id": "qBC3kE04PkQ", "title": "July 12, 2026", "channel": "Gianna Joyce", "channel_id": "UCvkiMyg2cjr-dDcBSK1IoUA", "thumbnail": "https://i.ytimg.com/vi/qBC3kE04PkQ/hqdefault.jpg", "duration_s": 7, "is_vertical": false, "views": 15634}, {"id": "YUVQeNKyedA", "title": "July 12, 2026", "channel": "Cassie", "channel_id": "UCrrFeKQMy7bYJ80emVdxl7A", "thumbnail": "https://i.ytimg.com/vi/YUVQeNKyedA/hqdefault.jpg", "duration_s": 9, "is_vertical": false, "views": 15774}, {"id": "VmF79UYFufE", "title": "12. Juli 2026", "channel": "felix_witherbrawl", "channel_id": "UCnDWCLROcNt3QU9iDj0wewg", "thumbnail": "https://i.ytimg.com/vi/VmF79UYFufE/hqdefault.jpg", "duration_s": 61, "is_vertical": false, "views": 577}, {"id": "INYo4QIpFMI", "title": "July 12, 2026", "channel": "And Then We", "channel_id": "UCh17fJRHVkTz_i7BoRVmnKg", "thumbnail": "https://i.ytimg.com/vi/INYo4QIpFMI/hqdefault.jpg", "duration_s": 123, "is_vertical": false, "views": 465}, {"id": "ZE-m30yt-wg", "title": "July 12, 2026", "channel": "Naty Mihut", "channel_id": "UCGZQP43eCe2X3Un74OC_3hQ", "thumbnail": "https://i.ytimg.com/vi/ZE-m30yt-wg/hqdefault.jpg", "duration_s": 23, "is_vertical": false, "views": 3469}, {"id": "w56VEqkhYj4", "title": "July 12, 2026", "channel": "Stellyn Fashion TV", "channel_id": "UCTRl6okDBiUIhut_15xiIrA", "thumbnail": "https://i.ytimg.com/vi/w56VEqkhYj4/hqdefault.jpg", "duration_s": 21, "is_vertical": false, "views": 734}, {"id": "Bp79plzgH_Q", "title": "12 июля 2026 г.", "channel": "dovud_samizoda", "channel_id": "UCAkPPzBTUVJN2M652qTQARg", "thumbnail": "https://i.ytimg.com/vi/Bp79plzgH_Q/hqdefault.jpg", "duration_s": 38, "is_vertical": false, "views": 5456}, {"id": "GUoJQIgu5hs", "title": "12. Juli 2026", "channel": "Zocker Ben", "channel_id": "UC65Aey6aCBv1Ip23F-e-80w", "thumbnail": "https://i.ytimg.com/vi/GUoJQIgu5hs/hqdefault.jpg", "duration_s": 33, "is_vertical": false, "views": 970}, {"id": "IFhH7nZ_amQ", "title": "12 ביולי 2026", "channel": "‏נועם יונה⚽️🕊️", "channel_id": "UCh7otWFWzTFhwmJahkxSzVA", "thumbnail": "https://i.ytimg.com/vi/IFhH7nZ_amQ/hqdefault.jpg", "duration_s": 12, "is_vertical": false, "views": 3296}, {"id": "8HSSf6PB8E4", "title": "12 de julho de 2026", "channel": "Alberttinha ", "channel_id": "UCcCIdyfVpfaIK2-kSQ0VSqw", "thumbnail": "https://i.ytimg.com/vi/8HSSf6PB8E4/hqdefault.jpg", "duration_s": 16, "is_vertical": false, "views": 1703}, {"id": "vEyidXdRJJI", "title": "12 июля 2026 г.", "channel": "Simpo Samo official", "channel_id": "UCJX3rH_E31RUrTnnzFFYV7Q", "thumbnail": "https://i.ytimg.com/vi/vEyidXdRJJI/hqdefault.jpg", "duration_s": 28, "is_vertical": false, "views": 8791}, {"id": "bD6KXZl51yU", "title": "July 12, 2026", "channel": "Barrr_None", "channel_id": "UC0EPLsmIgaQSw6rhPKfbGwQ", "thumbnail": "https://i.ytimg.com/vi/bD6KXZl51yU/hqdefault.jpg", "duration_s": 63, "is_vertical": false, "views": 31426}, {"id": "t7xkSYCJ3e0", "title": "July 12, 2026", "channel": "Kute's Lifestyle", "channel_id": "UCOa2X_uNP2l_OHolm4eXpVQ", "thumbnail": "https://i.ytimg.com/vi/t7xkSYCJ3e0/hqdefault.jpg", "duration_s": 100, "is_vertical": false, "views": 487}, {"id": "GhSAk8Bfubc", "title": "12 Temmuz 2026", "channel": "efewissie", "channel_id": "UCjzvhml4qj_1ULa71fppF5A", "thumbnail": "https://i.ytimg.com/vi/GhSAk8Bfubc/hqdefault.jpg", "duration_s": 8, "is_vertical": false, "views": 22969}, {"id": "nuZ6SBDDXhY", "title": "12. Juli 2026", "channel": "Katrin Schneider", "channel_id": "UCkqkxKjv1GGsAC6sSgU8cYQ", "thumbnail": "https://i.ytimg.com/vi/nuZ6SBDDXhY/hqdefault.jpg", "duration_s": 20, "is_vertical": false, "views": 838}, {"id": "rzrGNxz1Sr4", "title": "July 12, 2026", "channel": "Sandra Perez", "channel_id": "UCzQFBG_aGXkxgIqXqOTHpyQ", "thumbnail": "https://i.ytimg.com/vi/rzrGNxz1Sr4/hqdefault.jpg", "duration_s": 156, "is_vertical": false, "views": 9476}, {"id": "DhFqEGcutK8", "title": "11 PM Headlines | 12 July 2026 | Today’s Top News Updates | Odisha Latest News | Argus News", "channel": "Argus News", "channel_id": "UCwBK7Cdk0wq8rCjxcvaoHzg", "thumbnail": "https://i.ytimg.com/vi/DhFqEGcutK8/hqdefault.jpg", "duration_s": 100, "is_vertical": false, "views": 7912}, {"id": "BN76x-yzmo0", "title": "12. Juli 2026", "channel": "Paula Doeringer", "channel_id": "UCfw95ofzU4UvN2Mskz5ONJQ", "thumbnail": "https://i.ytimg.com/vi/BN76x-yzmo0/hqdefault.jpg", "duration_s": 30, "is_vertical": false, "views": 13633}, {"id": "X_QdAoy_0Po", "title": "July 12, 2026", "channel": "Tauheed__vlog ", "channel_id": "UCSZQhO0nHPQXqjruYFx0ycw", "thumbnail": "https://i.ytimg.com/vi/X_QdAoy_0Po/hqdefault.jpg", "duration_s": 35, "is_vertical": false, "views": 3029}, {"id": "0EJYDlP6ifQ", "title": "12. Juli 2026", "channel": "Paula Doeringer", "channel_id": "UCfw95ofzU4UvN2Mskz5ONJQ", "thumbnail": "https://i.ytimg.com/vi/0EJYDlP6ifQ/hqdefault.jpg", "duration_s": 15, "is_vertical": false, "views": 15259}, {"id": "c26ymAb_m4s", "title": "12. Juli 2026", "channel": "Paula Doeringer", "channel_id": "UCfw95ofzU4UvN2Mskz5ONJQ", "thumbnail": "https://i.ytimg.com/vi/c26ymAb_m4s/hqdefault.jpg", "duration_s": 28, "is_vertical": false, "views": 5429}, {"id": "hxdkT8A4JJg", "title": "12 juillet 2026", "channel": "Drissa lalaby ", "channel_id": "UCg_QPVD18HXty4ifEZCRCog", "thumbnail": "https://i.ytimg.com/vi/hxdkT8A4JJg/hqdefault.jpg", "duration_s": 64, "is_vertical": false, "views": 565}, {"id": "Fd2irqTpsfM", "title": "12 July 2026", "channel": "Adonay", "channel_id": "UCoZ0jESV2Jyy4JJjeDeHs_A", "thumbnail": "https://i.ytimg.com/vi/Fd2irqTpsfM/hqdefault.jpg", "duration_s": 126, "is_vertical": false, "views": 15760}, {"id": "oB_wj6beLvc", "title": "12 июля 2026 г.", "channel": "Кoppel Fam", "channel_id": "UCuMpcHKHQFFRxnT_7dCEyWQ", "thumbnail": "https://i.ytimg.com/vi/oB_wj6beLvc/hqdefault.jpg", "duration_s": 11, "is_vertical": false, "views": 3722}, {"id": "M2kCH7JOPCs", "title": "12 July 2026", "channel": "Asli Swa", "channel_id": "UCXWOt1LYNKsUvucTwgsMKDA", "thumbnail": "https://i.ytimg.com/vi/M2kCH7JOPCs/hqdefault.jpg", "duration_s": 14, "is_vertical": false, "views": 3936}, {"id": "e90FjKzljnE", "title": "12 липня 2026 р.", "channel": "lisoryb24", "channel_id": "UCpVkQ3tJDhvzSqehX5j-DrQ", "thumbnail": "https://i.ytimg.com/vi/e90FjKzljnE/hqdefault.jpg", "duration_s": 19, "is_vertical": false, "views": 11301}, {"id": "ULgTKHh7uGM", "title": "12 Juli 2026", "channel": "Basuki Suwarno", "channel_id": "UCF1PACdx2ar_mvt84bbITjQ", "thumbnail": "https://i.ytimg.com/vi/ULgTKHh7uGM/hqdefault.jpg", "duration_s": 155, "is_vertical": false, "views": 9055}, {"id": "XSzQTYPzyhM", "title": "12 июля 2026 г.", "channel": "Світлана Базаренко Привоз ", "channel_id": "UCfohpEzG_aA0XjICMEn8fHQ", "thumbnail": "https://i.ytimg.com/vi/XSzQTYPzyhM/hqdefault.jpg", "duration_s": 57, "is_vertical": false, "views": 10558}, {"id": "3jnALQpY7Bc", "title": "12 July 2026", "channel": "Dr Gavin Ashenden", "channel_id": "UCDsEZkV8hLSQJbWyR_B4arQ", "thumbnail": "https://i.ytimg.com/vi/3jnALQpY7Bc/hqdefault.jpg", "duration_s": 68, "is_vertical": false, "views": 5256}, {"id": "ZlPV3jylIUo", "title": "July 12, 2026", "channel": "MushyKinz", "channel_id": "UCKfkxY75LyAZpoRiqTqtUyA", "thumbnail": "https://i.ytimg.com/vi/ZlPV3jylIUo/hqdefault.jpg", "duration_s": 45, "is_vertical": false, "views": 15203}, {"id": "Hrq7_XJqOYo", "title": "12 July 2026", "channel": "BALRAJ AKKAM1", "channel_id": "UCe_vJpyeepnZSJ361t0l-wA", "thumbnail": "https://i.ytimg.com/vi/Hrq7_XJqOYo/hqdefault.jpg", "duration_s": 15, "is_vertical": false, "views": 481260}, {"id": "DkMFcRcYRYY", "title": "July 12, 2026", "channel": "Shakira Maryland", "channel_id": "UCPhelmUbL03WVXs_I4s9QKQ", "thumbnail": "https://i.ytimg.com/vi/DkMFcRcYRYY/hqdefault.jpg", "duration_s": 11, "is_vertical": false, "views": 6587}, {"id": "2BhRcEDZDyM", "title": "12 июля 2026 г.", "channel": "Chagaev", "channel_id": "UC8l1Y559u9iuJsMIqRBd8Kw", "thumbnail": "https://i.ytimg.com/vi/2BhRcEDZDyM/hqdefault.jpg", "duration_s": 30, "is_vertical": false, "views": 49092}, {"id": "tvGvJoiOOSQ", "title": "12 июля 2026 г.", "channel": "Лера и Саша ", "channel_id": "UChfjRbsZgAmj1kKvN7MUnkA", "thumbnail": "https://i.ytimg.com/vi/tvGvJoiOOSQ/hqdefault.jpg", "duration_s": 17, "is_vertical": false, "views": 17350}, {"id": "fUZ2xxghxF0", "title": "July 12, 2026", "channel": "Jamos", "channel_id": "UCCtmNFSbTi1bVtoa3j1V9cg", "thumbnail": "https://i.ytimg.com/vi/fUZ2xxghxF0/hqdefault.jpg", "duration_s": 11, "is_vertical": false, "views": 5701}, {"id": "TD87OmOU940", "title": "12 Juli 2026", "channel": "BID HUMAS POLDA RIAU", "channel_id": "UCFJxStZliBiJqZVgOrSvVaA", "thumbnail": "https://i.ytimg.com/vi/TD87OmOU940/hqdefault.jpg", "duration_s": 71, "is_vertical": false, "views": 922}, {"id": "zQdgxiXpGYo", "title": "12 luglio 2026", "channel": "Giuly_officiall", "channel_id": "UCZZCS7CGkmzFPwW-lzYoJzA", "thumbnail": "https://i.ytimg.com/vi/zQdgxiXpGYo/hqdefault.jpg", "duration_s": 9, "is_vertical": false, "views": 8236}, {"id": "Yqs2rf8BaSQ", "title": "7 PM Headlines | 12 July 2026 | Today’s Top News Updates | Odisha Latest News | Argus News", "channel": "Argus News", "channel_id": "UCwBK7Cdk0wq8rCjxcvaoHzg", "thumbnail": "https://i.ytimg.com/vi/Yqs2rf8BaSQ/hqdefault.jpg", "duration_s": 95, "is_vertical": false, "views": 26369}, {"id": "-KjzZp_pNdg", "title": "12 de julho 2026", "channel": "casalnovaiguacu", "channel_id": "UC_hHnmK4tXaXChzosV_G6UQ", "thumbnail": "https://i.ytimg.com/vi/-KjzZp_pNdg/hqdefault.jpg", "duration_s": 6, "is_vertical": false, "views": 11368}, {"id": "BK5M52IKRKM", "title": "12 Juli 2026", "channel": "zuhana laila", "channel_id": "UCPxEi71Oq-nAhZP11ei0sNw", "thumbnail": "https://i.ytimg.com/vi/BK5M52IKRKM/hqdefault.jpg", "duration_s": 11, "is_vertical": false, "views": 1440}, {"id": "3TOW9EpJtuU", "title": "12. Juli 2026", "channel": "Jonnyonbike_", "channel_id": "UC0oIyfRHzdvanZLmyadwlBw", "thumbnail": "https://i.ytimg.com/vi/3TOW9EpJtuU/hqdefault.jpg", "duration_s": 19, "is_vertical": false, "views": 1278}, {"id": "Cn87RkCGqlE", "title": "12 July, 2026", "channel": "Our Around", "channel_id": "UCxRmVY120hAi4EvlnWpofUQ", "thumbnail": "https://i.ytimg.com/vi/Cn87RkCGqlE/hqdefault.jpg", "duration_s": 34, "is_vertical": false, "views": 32942}, {"id": "t2-aF4cMNAs", "title": "SABCNews PM Headlines @15H00 | 12 July 2026", "channel": "SABC News", "channel_id": "UC8yH-uI81UUtEMDsowQyx1g", "thumbnail": "https://i.ytimg.com/vi/t2-aF4cMNAs/hqdefault.jpg", "duration_s": 101, "is_vertical": false, "views": 2376}, {"id": "UKOgBgSPv_E", "title": "12 июля 2026 г.", "channel": "Эй, кучерявая", "channel_id": "UC07s2OArkmMG_sx1H2YrdgQ", "thumbnail": "https://i.ytimg.com/vi/UKOgBgSPv_E/hqdefault.jpg", "duration_s": 12, "is_vertical": false, "views": 5250}, {"id": "ziDbxbqwRgM", "title": "12 July 2026", "channel": "Mr1million ", "channel_id": "UCV72Aiu_6fG6pOLpaUxvV-g", "thumbnail": "https://i.ytimg.com/vi/ziDbxbqwRgM/hqdefault.jpg", "duration_s": 16, "is_vertical": false, "views": 12223}, {"id": "nUzV9NrRUHI", "title": "12 July 2026", "channel": "Philip Olubakin", "channel_id": "UClqTn4d0brtqiRC92KkOZag", "thumbnail": "https://i.ytimg.com/vi/nUzV9NrRUHI/hqdefault.jpg", "duration_s": 137, "is_vertical": false, "views": 17771}, {"id": "5FYy94eF07E", "title": "12 Juli 2026", "channel": "Dunia Kafi Khalisa", "channel_id": "UCTVqtMcaJq9Ifz-8WiLItPg", "thumbnail": "https://i.ytimg.com/vi/5FYy94eF07E/hqdefault.jpg", "duration_s": 26, "is_vertical": false, "views": 21964}, {"id": "hRWxIkLH-v4", "title": "12 Juli 2026", "channel": "BERITA TERBARU ", "channel_id": "UC_MhfoU4q_8ykfhQynpH6eA", "thumbnail": "https://i.ytimg.com/vi/hRWxIkLH-v4/hqdefault.jpg", "duration_s": 6, "is_vertical": false, "views": 179436}, {"id": "qhcx4u2m_d8", "title": "July 12, 2026", "channel": "二戰編年史", "channel_id": "UCgwzDmLOZuMJWTJPMEGK1hQ", "thumbnail": "https://i.ytimg.com/vi/qhcx4u2m_d8/hqdefault.jpg", "duration_s": 59, "is_vertical": false, "views": 2334}, {"id": "wsPfUlarCg8", "title": "July 12, 2026", "channel": "OBLIS COLLECTION", "channel_id": "UCPppOcA2n7RUnusmJdb_zhQ", "thumbnail": "https://i.ytimg.com/vi/wsPfUlarCg8/hqdefault.jpg", "duration_s": 13, "is_vertical": false, "views": 1991}, {"id": "oMqcHYEWgIs", "title": "12. Juli 2026", "channel": "🐲Puppet maker🐉", "channel_id": "UCKmQ998V9PoCgZXUXTvZTxA", "thumbnail": "https://i.ytimg.com/vi/oMqcHYEWgIs/hqdefault.jpg", "duration_s": 16, "is_vertical": false, "views": 1594}, {"id": "MR4lFxkiVi4", "title": "12 июля 2026 г.", "channel": "цыганский мир, в 60 секунд", "channel_id": "UC3PdD9VT9DDrrXYsih6t2_g", "thumbnail": "https://i.ytimg.com/vi/MR4lFxkiVi4/hqdefault.jpg", "duration_s": 14, "is_vertical": false, "views": 79554}, {"id": "zYx1d4PcEpE", "title": "12 Juli 2026", "channel": "Abdul Qodir OFFICIAL ", "channel_id": "UCrQs_OqVv80cT2GCkh05gXA", "thumbnail": "https://i.ytimg.com/vi/zYx1d4PcEpE/hqdefault.jpg", "duration_s": 16, "is_vertical": false, "views": 12812}, {"id": "8MTjS9-CXMw", "title": "12 Juli 2026", "channel": "Ade irma Irma", "channel_id": "UCHTayYTzKZSRXEg8Vtv72_Q", "thumbnail": "https://i.ytimg.com/vi/8MTjS9-CXMw/hqdefault.jpg", "duration_s": 14, "is_vertical": false, "views": 2276}, {"id": "KgvhZRX8UqE", "title": "July 12, 2026", "channel": "Limb Loss Boss ", "channel_id": "UCgyPDDyFkRqoilq8NgGSGPQ", "thumbnail": "https://i.ytimg.com/vi/KgvhZRX8UqE/hqdefault.jpg", "duration_s": 151, "is_vertical": false, "views": 5859}, {"id": "-rgWDvlOzY4", "title": "12 июля 2026 г.", "channel": "SHumbolani Dodasi ", "channel_id": "UCo08mNVZ40rRzs9NJcWKmlw", "thumbnail": "https://i.ytimg.com/vi/-rgWDvlOzY4/hqdefault.jpg", "duration_s": 33, "is_vertical": false, "views": 18464}, {"id": "X0vWzbrcvME", "title": "12. Juli 2026", "channel": "Highlightsofficial", "channel_id": "UCkgTDIb5WwJCSBFIR5U6GiA", "thumbnail": "https://i.ytimg.com/vi/X0vWzbrcvME/hqdefault.jpg", "duration_s": 14, "is_vertical": false, "views": 1037}, {"id": "0wRDBv3sLDo", "title": "12. Juli 2026", "channel": "marie&jonas", "channel_id": "UCc6jeBp4oK4-c9CXQpReC0g", "thumbnail": "https://i.ytimg.com/vi/0wRDBv3sLDo/hqdefault.jpg", "duration_s": 76, "is_vertical": false, "views": 7775}, {"id": "RF3XwV59Z2I", "title": "12. Juli 2026", "channel": "Mathias Garnelen Aquarium", "channel_id": "UCkYBxfQtjmCMaX8Kme7Fkrw", "thumbnail": "https://i.ytimg.com/vi/RF3XwV59Z2I/hqdefault.jpg", "duration_s": 21, "is_vertical": false, "views": 965}, {"id": "rrrzDbMKyZY", "title": "12. Juli 2026", "channel": "Big Sister Secrets ", "channel_id": "UCVF8OM-xdkaBCU5YFkm4pgg", "thumbnail": "https://i.ytimg.com/vi/rrrzDbMKyZY/hqdefault.jpg", "duration_s": 11, "is_vertical": false, "views": 851}, {"id": "sczaLqtMfcM", "title": "12. juli 2026.", "channel": "JASMINA", "channel_id": "UCIhfegmo5g-l4Au8NqkfTQQ", "thumbnail": "https://i.ytimg.com/vi/sczaLqtMfcM/hqdefault.jpg", "duration_s": 11, "is_vertical": false, "views": 5376}, {"id": "TENDq8WwxQ4", "title": "12. Juli 2026", "channel": "𝓑𝓻𝓸𝓴𝓮𝓷 𝓗𝓮𝓪𝓻𝓽 ", "channel_id": "UCKCqIy3WupWfpqE7BVsucuQ", "thumbnail": "https://i.ytimg.com/vi/TENDq8WwxQ4/hqdefault.jpg", "duration_s": 87, "is_vertical": false, "views": 1935}, {"id": "LDTjzmhrHh4", "title": "12 Juli 2026", "channel": "VINZZ⚡", "channel_id": "UCp3oGXBRnUHBGJ20cD_kh3Q", "thumbnail": "https://i.ytimg.com/vi/LDTjzmhrHh4/hqdefault.jpg", "duration_s": 34, "is_vertical": false, "views": 1171}, {"id": "1a5TzAL2LjM", "title": "12 Juli 2026", "channel": "Luns  Channel", "channel_id": "UC8EfvCRyITkoLi7ZQ6QKZOw", "thumbnail": "https://i.ytimg.com/vi/1a5TzAL2LjM/hqdefault.jpg", "duration_s": 121, "is_vertical": false, "views": 2716}, {"id": "M75-Iatz3j0", "title": "12. Juli 2026", "channel": "🐲Puppet maker🐉", "channel_id": "UCKmQ998V9PoCgZXUXTvZTxA", "thumbnail": "https://i.ytimg.com/vi/M75-Iatz3j0/hqdefault.jpg", "duration_s": 16, "is_vertical": false, "views": 1211}, {"id": "zNG9T05SgRI", "title": "12 July 2026", "channel": "keeno & liz", "channel_id": "UC3RUccwJ036sQ7Pxpi9mlOg", "thumbnail": "https://i.ytimg.com/vi/zNG9T05SgRI/hqdefault.jpg", "duration_s": 54, "is_vertical": false, "views": 6347}, {"id": "NhygvLiY0-o", "title": "12 Juli 2026", "channel": "hafiz abinaya", "channel_id": "UCKpfH4IqCOtSBkZahlmsuug", "thumbnail": "https://i.ytimg.com/vi/NhygvLiY0-o/hqdefault.jpg", "duration_s": 16, "is_vertical": false, "views": 1878}, {"id": "u10AhuU-n58", "title": "12. Juli 2026", "channel": "immo", "channel_id": "UCT02Lzb8stamI0wYrGNYb-w", "thumbnail": "https://i.ytimg.com/vi/u10AhuU-n58/hqdefault.jpg", "duration_s": 23, "is_vertical": false, "views": 1048}, {"id": "dzJMO8mBKAs", "title": "12. Juli 2026", "channel": "Leon und Max die zwei Brüder ", "channel_id": "UCyfYH32mmFdKEIU75odbW9A", "thumbnail": "https://i.ytimg.com/vi/dzJMO8mBKAs/hqdefault.jpg", "duration_s": 25, "is_vertical": false, "views": 1267}, {"id": "XUcTqCfEwrs", "title": "12. Juli 2026", "channel": "Sammy", "channel_id": "UC6tUEgKu7qh5udGTuO15ZUg", "thumbnail": "https://i.ytimg.com/vi/XUcTqCfEwrs/hqdefault.jpg", "duration_s": 7, "is_vertical": false, "views": 1642}, {"id": "XBaWwiqH3Uk", "title": "12. Juli 2026", "channel": "Highlightsofficial", "channel_id": "UCkgTDIb5WwJCSBFIR5U6GiA", "thumbnail": "https://i.ytimg.com/vi/XBaWwiqH3Uk/hqdefault.jpg", "duration_s": 12, "is_vertical": false, "views": 1034}, {"id": "2vd8ezGPt_k", "title": "July 12, 2026", "channel": "LovelyPawsVirgo", "channel_id": "UCed8OJFjLVB8e8sBowsesIw", "thumbnail": "https://i.ytimg.com/vi/2vd8ezGPt_k/hqdefault.jpg", "duration_s": 64, "is_vertical": false, "views": 1934}, {"id": "w-yNK_m0Hzc", "title": "12. Juli 2026", "channel": "Muhammad-Amin", "channel_id": "UCr9sZmgoOnl_CYSQJOgvO0Q", "thumbnail": "https://i.ytimg.com/vi/w-yNK_m0Hzc/hqdefault.jpg", "duration_s": 14, "is_vertical": false, "views": 1878}, {"id": "Orf5SoP5ksk", "title": "12 Juli 2026", "channel": "DORIA KITCHEN", "channel_id": "UCYzFUHDkXugNkS7Q_H2JfJw", "thumbnail": "https://i.ytimg.com/vi/Orf5SoP5ksk/hqdefault.jpg", "duration_s": 16, "is_vertical": false, "views": 9485}, {"id": "h0jLVv_Fxxk", "title": "12. Juli 2026", "channel": "Reichshistorie", "channel_id": "UCegrIv-VzNRmIBJyOT8f3JQ", "thumbnail": "https://i.ytimg.com/vi/h0jLVv_Fxxk/hqdefault.jpg", "duration_s": 17, "is_vertical": false, "views": 1144}, {"id": "s89X2JTNA8c", "title": "July 12, 2026", "channel": "Riley ", "channel_id": "UCQ3pzLe_l6WkjK42oh4UjWQ", "thumbnail": "https://i.ytimg.com/vi/s89X2JTNA8c/hqdefault.jpg", "duration_s": 6, "is_vertical": false, "views": 11117}, {"id": "YOTHwAXy1KM", "title": "12. Juli 2026", "channel": "Die King of Pub", "channel_id": "UCwjamfpBFliXY3O-CpS1ANg", "thumbnail": "https://i.ytimg.com/vi/YOTHwAXy1KM/hqdefault.jpg", "duration_s": 16, "is_vertical": false, "views": 881}, {"id": "tspwXHwvSKE", "title": "12 Juli 2026", "channel": "dangdut mania", "channel_id": "UCFX1HmJzN-aXfbbovwaGLEQ", "thumbnail": "https://i.ytimg.com/vi/tspwXHwvSKE/hqdefault.jpg", "duration_s": 29, "is_vertical": false, "views": 10021}, {"id": "WaTq1q1861g", "title": "12. Juli 2026", "channel": "Beyt625", "channel_id": "UCmcA26wL2rY4LDlT6a0XiLw", "thumbnail": "https://i.ytimg.com/vi/WaTq1q1861g/hqdefault.jpg", "duration_s": 22, "is_vertical": false, "views": 1090}, {"id": "2HKuQuSV01M", "title": "12. Juli 2026", "channel": "JacobusMaximus", "channel_id": "UC0NT_99WEdXhiVAPeI4LHmg", "thumbnail": "https://i.ytimg.com/vi/2HKuQuSV01M/hqdefault.jpg", "duration_s": 37, "is_vertical": false, "views": 1061}, {"id": "W4U91p-BHBo", "title": "12. Juli 2026", "channel": "King is the best", "channel_id": "UCOcjyrz18Ef9346ZXLYDC0g", "thumbnail": "https://i.ytimg.com/vi/W4U91p-BHBo/hqdefault.jpg", "duration_s": 16, "is_vertical": false, "views": 1314}, {"id": "h8vWHZx3PpI", "title": "12. Juli 2026", "channel": "sara_love_drawing", "channel_id": "UCysB1USzTx4o8ONtTW2oNOQ", "thumbnail": "https://i.ytimg.com/vi/h8vWHZx3PpI/hqdefault.jpg", "duration_s": 15, "is_vertical": false, "views": 973}, {"id": "44uZ9Ar2EEs", "title": "12. Juli 2026", "channel": "Robloxgam", "channel_id": "UCteZP6FUf3-Ds2U5tqkT4sg", "thumbnail": "https://i.ytimg.com/vi/44uZ9Ar2EEs/hqdefault.jpg", "duration_s": 18, "is_vertical": false, "views": 1434}, {"id": "q1zKRI2H_Pg", "title": "12. Juli 2026", "channel": "kobra", "channel_id": "UCAMN7-5QaL9_sjWElwO2p5g", "thumbnail": "https://i.ytimg.com/vi/q1zKRI2H_Pg/hqdefault.jpg", "duration_s": 21, "is_vertical": false, "views": 1003}, {"id": "YgYU1Dui_NE", "title": "12. Juli 2026", "channel": "Givemeyourmoney", "channel_id": "UCnqVta5ER2W7-SwoOAgXQoA", "thumbnail": "https://i.ytimg.com/vi/YgYU1Dui_NE/hqdefault.jpg", "duration_s": 16, "is_vertical": false, "views": 8084}, {"id": "3hrTyFaNvoo", "title": "12. Juli 2026", "channel": "anne8.0x ceramicgermany", "channel_id": "UClukOsnzuAR6v8mS74rruCA", "thumbnail": "https://i.ytimg.com/vi/3hrTyFaNvoo/hqdefault.jpg", "duration_s": 16, "is_vertical": false, "views": 1891}, {"id": "8vAiJ67bHqo", "title": "12. Juli 2026", "channel": "Givemeyourmoney", "channel_id": "UCnqVta5ER2W7-SwoOAgXQoA", "thumbnail": "https://i.ytimg.com/vi/8vAiJ67bHqo/hqdefault.jpg", "duration_s": 16, "is_vertical": false, "views": 550}, {"id": "3nZp7nplF0U", "title": "12. Juli 2026", "channel": "Detlef Michel", "channel_id": "UCG0wG7Mx9M5JE0Io2l5oQVA", "thumbnail": "https://i.ytimg.com/vi/3nZp7nplF0U/hqdefault.jpg", "duration_s": 39, "is_vertical": false, "views": 1219}, {"id": "Qt0NmffR_CE", "title": "12. Juli 2026", "channel": "bella_S", "channel_id": "UCh8JGC8mk3zDwqQWTBkEBlA", "thumbnail": "https://i.ytimg.com/vi/Qt0NmffR_CE/hqdefault.jpg", "duration_s": 18, "is_vertical": false, "views": 737}, {"id": "BmrZZ5ptLW4", "title": "12. Juli 2026", "channel": "lea", "channel_id": "UCc7SXghNRJV8CQ_9fqcH5vg", "thumbnail": "https://i.ytimg.com/vi/BmrZZ5ptLW4/hqdefault.jpg", "duration_s": 11, "is_vertical": false, "views": 1336}, {"id": "jm-i6rejNco", "title": "12. Juli 2026", "channel": "Mihrimah Herz ", "channel_id": "UCoLHBsOLg8yWb_uh2cZTk4g", "thumbnail": "https://i.ytimg.com/vi/jm-i6rejNco/hqdefault.jpg", "duration_s": 16, "is_vertical": false, "views": 1580}, {"id": "k3kNwsKkOT8", "title": "12 Juli 2026", "channel": "Michael Schloter", "channel_id": "UC-CYgbh7gLplBJzMwL-R_1Q", "thumbnail": "https://i.ytimg.com/vi/k3kNwsKkOT8/hqdefault.jpg", "duration_s": 53, "is_vertical": false, "views": 1258}, {"id": "omBOgGSq0zs", "title": "12. Juli 2026", "channel": "pauline67cool", "channel_id": "UCw5EjEI--Iuu6j22yIV0ZYQ", "thumbnail": "https://i.ytimg.com/vi/omBOgGSq0zs/hqdefault.jpg", "duration_s": 61, "is_vertical": false, "views": 1246}, {"id": "GhjgM4ifAfc", "title": "12. Juli 2026", "channel": "Simone Kiefer", "channel_id": "UC_VxQ4ezt7JDEf7vl5jj7Bg", "thumbnail": "https://i.ytimg.com/vi/GhjgM4ifAfc/hqdefault.jpg", "duration_s": 30, "is_vertical": false, "views": 863}, {"id": "hsew3B6oQCw", "title": "12. Juli 2026", "channel": "studyflowwithangi", "channel_id": "UCZT6TWg8tDZUlB1-c6dF24A", "thumbnail": "https://i.ytimg.com/vi/hsew3B6oQCw/hqdefault.jpg", "duration_s": 72, "is_vertical": false, "views": 1197}, {"id": "G-d2gdQgrXs", "title": "12. Juli 2026", "channel": "Derek⚽️🤙", "channel_id": "UCCCZ734y0nPfFsufxp6rNQg", "thumbnail": "https://i.ytimg.com/vi/G-d2gdQgrXs/hqdefault.jpg", "duration_s": 16, "is_vertical": false, "views": 1451}, {"id": "sSz-fZyhdBo", "title": "12. Juli 2026", "channel": "Franziska Thieme ", "channel_id": "UCvL5QaqJ9EUlJHQYf-4WWAQ", "thumbnail": "https://i.ytimg.com/vi/sSz-fZyhdBo/hqdefault.jpg", "duration_s": 16, "is_vertical": false, "views": 935}, {"id": "93xfgoAkOzQ", "title": "12. Juli 2026", "channel": "Samuel", "channel_id": "UCWVF_iqZzYfOp4h4Ejo1gxw", "thumbnail": "https://i.ytimg.com/vi/93xfgoAkOzQ/hqdefault.jpg", "duration_s": 19, "is_vertical": false, "views": 1072}, {"id": "2wdqglC0drA", "title": "12. Juli 2026", "channel": "Toca world", "channel_id": "UCHVOdy0j37KnTXXfSwLIjDw", "thumbnail": "https://i.ytimg.com/vi/2wdqglC0drA/hqdefault.jpg", "duration_s": 20, "is_vertical": false, "views": 1287}, {"id": "avyRKIsynQw", "title": "12. Juli 2026", "channel": "Lili", "channel_id": "UCnr0zJCq4eIbGfsIOYKemwQ", "thumbnail": "https://i.ytimg.com/vi/avyRKIsynQw/hqdefault.jpg", "duration_s": 11, "is_vertical": false, "views": 1189}, {"id": "jM5ZSniLgdY", "title": "12. Juli 2026", "channel": "Tyler und mehr ", "channel_id": "UCSRmSdIrBC9KOn3fz8LVXzA", "thumbnail": "https://i.ytimg.com/vi/jM5ZSniLgdY/hqdefault.jpg", "duration_s": 83, "is_vertical": false, "views": 1177}, {"id": "X-EOeUk5eUg", "title": "12. Juli 2026", "channel": "Mimi💖", "channel_id": "UCavjRD4-63Viq1Fa6S8boAQ", "thumbnail": "https://i.ytimg.com/vi/X-EOeUk5eUg/hqdefault.jpg", "duration_s": 18, "is_vertical": false, "views": 1843}, {"id": "ZpXsC50DBuo", "title": "12. Juli 2026", "channel": "Roblox Kanal, CO", "channel_id": "UCkUG-7G9uT7TGxl9UXGwdmg", "thumbnail": "https://i.ytimg.com/vi/ZpXsC50DBuo/hqdefault.jpg", "duration_s": 18, "is_vertical": false, "views": 1619}, {"id": "axWbd9pseLo", "title": "12 July 2026", "channel": "Nisha's life ", "channel_id": "UCIjjWnpP880sxJPfiwwx9sQ", "thumbnail": "https://i.ytimg.com/vi/axWbd9pseLo/hqdefault.jpg", "duration_s": 8, "is_vertical": false, "views": 16142}, {"id": "8M_cdobUMMo", "title": "12. Juli 2026", "channel": "Shana", "channel_id": "UCUhJ-XwTPzV9QrmHSwWh90Q", "thumbnail": "https://i.ytimg.com/vi/8M_cdobUMMo/hqdefault.jpg", "duration_s": 22, "is_vertical": false, "views": 1069}, {"id": "rArycNoINh8", "title": "12. Juli 2026", "channel": "Murat Bicer", "channel_id": "UCkx8iX8Xm4X_7hTjwluSuIQ", "thumbnail": "https://i.ytimg.com/vi/rArycNoINh8/hqdefault.jpg", "duration_s": 25, "is_vertical": false, "views": 946}, {"id": "px5ELC2hX5E", "title": "12. Juli 2026", "channel": "Fatih.Servet", "channel_id": "UCf1HP4UiwJS0awNdlLwFzug", "thumbnail": "https://i.ytimg.com/vi/px5ELC2hX5E/hqdefault.jpg", "duration_s": 18, "is_vertical": false, "views": 1181}, {"id": "l37iDh3v49w", "title": "12. Juli 2026", "channel": "Nikebro", "channel_id": "UCHaV3ccz7jIWHki432_dwPQ", "thumbnail": "https://i.ytimg.com/vi/l37iDh3v49w/hqdefault.jpg", "duration_s": 16, "is_vertical": false, "views": 1063}, {"id": "aYykMXdLWO8", "title": "12. Juli 2026", "channel": "LeoFn12", "channel_id": "UCLW3TUC2p6YAxPZjflcH8jg", "thumbnail": "https://i.ytimg.com/vi/aYykMXdLWO8/hqdefault.jpg", "duration_s": 16, "is_vertical": false, "views": 1398}, {"id": "SahAvoGButE", "title": "12. Juli 2026", "channel": "Mila", "channel_id": "UCg53hj7F16bB9EQWL2XCEDg", "thumbnail": "https://i.ytimg.com/vi/SahAvoGButE/hqdefault.jpg", "duration_s": 51, "is_vertical": false, "views": 1014}, {"id": "aU19qpzhb6w", "title": "12 Juli 2026", "channel": "Basuki Suwarno", "channel_id": "UCF1PACdx2ar_mvt84bbITjQ", "thumbnail": "https://i.ytimg.com/vi/aU19qpzhb6w/hqdefault.jpg", "duration_s": 50, "is_vertical": false, "views": 12570}, {"id": "3WeACzdg8mM", "title": "12-iyul, 2026", "channel": "𝐉𝐚𝐬𝐦𝐢𝐧𝐚 𝐬𝐡𝐨𝐩𝐩𝐢𝐧𝐠", "channel_id": "UCkp0QoPlm7t5ceVL8gheExQ", "thumbnail": "https://i.ytimg.com/vi/3WeACzdg8mM/hqdefault.jpg", "duration_s": 14, "is_vertical": false, "views": 18092}, {"id": "NAUy6-aj-1w", "title": "12. Juli 2026", "channel": "cyprian", "channel_id": "UCfSs2OLCmMK1C0Ub6-Bihrg", "thumbnail": "https://i.ytimg.com/vi/NAUy6-aj-1w/hqdefault.jpg", "duration_s": 64, "is_vertical": false, "views": 3670}, {"id": "XnIbIaypnhI", "title": "12. Juli 2026", "channel": "lonsTony", "channel_id": "UCwNqF6Z7Ux7xJnhcpZ0yxtg", "thumbnail": "https://i.ytimg.com/vi/XnIbIaypnhI/hqdefault.jpg", "duration_s": 20, "is_vertical": false, "views": 3351}, {"id": "apGZ7vwjleM", "title": "12. Juli 2026", "channel": "stemaxma", "channel_id": "UCmcBnMsKEPmYdvHDcS-eAjg", "thumbnail": "https://i.ytimg.com/vi/apGZ7vwjleM/hqdefault.jpg", "duration_s": 70, "is_vertical": false, "views": 9291}, {"id": "dtYYbfHdk5A", "title": "12. Juli 2026", "channel": "Raccoons ", "channel_id": "UCDOqM15mCnuJDJkBhT3lJPA", "thumbnail": "https://i.ytimg.com/vi/dtYYbfHdk5A/hqdefault.jpg", "duration_s": 16, "is_vertical": false, "views": 1242}, {"id": "v0q4SmUGtqo", "title": "12. Juli 2026", "channel": "Hajijan GMBH", "channel_id": "UCPeNnMFuK8hmVL1HUQSTUgQ", "thumbnail": "https://i.ytimg.com/vi/v0q4SmUGtqo/hqdefault.jpg", "duration_s": 20, "is_vertical": false, "views": 898}, {"id": "yXbh92d7Q_Y", "title": "12. Juli 2026", "channel": "Sulamita _Roblox", "channel_id": "UC0Rhx7uFRyu0ujDJ5nLKjow", "thumbnail": "https://i.ytimg.com/vi/yXbh92d7Q_Y/hqdefault.jpg", "duration_s": 14, "is_vertical": false, "views": 909}, {"id": "No6gcShse2U", "title": "12. Juli 2026", "channel": "lonsTony", "channel_id": "UCwNqF6Z7Ux7xJnhcpZ0yxtg", "thumbnail": "https://i.ytimg.com/vi/No6gcShse2U/hqdefault.jpg", "duration_s": 14, "is_vertical": false, "views": 6297}, {"id": "py_TyQcuraA", "title": "12 Juli 2026", "channel": "Rika Family", "channel_id": "UCs70RPXneK05Q-pNZqFVGAQ", "thumbnail": "https://i.ytimg.com/vi/py_TyQcuraA/hqdefault.jpg", "duration_s": 24, "is_vertical": false, "views": 3578}, {"id": "kx5aheIHn8M", "title": "12. Juli 2026", "channel": "David Mettke", "channel_id": "UCIQ691t_34Tlt_uM5dmlBog", "thumbnail": "https://i.ytimg.com/vi/kx5aheIHn8M/hqdefault.jpg", "duration_s": 25, "is_vertical": false, "views": 962}, {"id": "rtUHPnaho7o", "title": "12. Juli 2026", "channel": "lonsTony", "channel_id": "UCwNqF6Z7Ux7xJnhcpZ0yxtg", "thumbnail": "https://i.ytimg.com/vi/rtUHPnaho7o/hqdefault.jpg", "duration_s": 15, "is_vertical": false, "views": 14539}, {"id": "ZAaRPcJXLNI", "title": "12 July 2026", "channel": "stevie_xo", "channel_id": "UCBC9jbg6_Cn71RDSqfciiRg", "thumbnail": "https://i.ytimg.com/vi/ZAaRPcJXLNI/hqdefault.jpg", "duration_s": 10, "is_vertical": false, "views": 40309}]